{"title":"FLO ─ New Track","url":"https://www.music-flo.com/new/track?sortType=KPOP","favicon":"https://www.music-flo.com/favicon.ico","elements":[{"title":"논해 (Feat. JUSTHIS) (Prod. CODE KUNST)","contents":"<!--fragment#b6d1ea1370#head-->개코<!--fragment#b6d1ea1370#tail-->","link":"https://www.music-flo.com/detail/album/edzhayoia/albumtrack","retrieved":1634960420204,"image":"https://cdn.music-flo.com/image/v2/album/731/819/06/04/406819731_616e7a82_s.jpg?1634630278984/dims/resize/140x140/quality/90"},{"title":"흥해라","contents":"<!--fragment#12ca70824af#head-->박서진<!--fragment#12ca70824af#tail-->","link":"https://www.music-flo.com/detail/album/edzhioded/albumtrack","retrieved":1634960420205,"image":"https://cdn.music-flo.com/image/v2/album/040/837/06/04/406837040_61723ed1_s.jpg?1634877140164/dims/resize/140x140/quality/90"},{"title":"HUMAN (Acapella)","contents":"<!--fragment#159fe1a49a3#head-->Untell (언텔)<!--fragment#159fe1a49a3#tail-->","link":"https://www.music-flo.com/detail/album/edzhnealh/albumtrack","retrieved":1634960420216,"image":"https://cdn.music-flo.com/image/v2/album/158/824/06/04/406824158_616fb732_o.jpeg?1634711347134/dims/resize/140x140/quality/90"},{"title":"Rock with you","contents":"<!--fragment#83d4ff0327#head-->세븐틴 (SEVENTEEN)<!--fragment#83d4ff0327#tail-->","link":"https://www.music-flo.com/detail/album/edzhizddi/albumtrack","retrieved":1634878179450,"image":"https://cdn.music-flo.com/image/v2/album/003/836/06/04/406836003_6172118f_s.jpg?1634865552945/dims/resize/140x140/quality/90"},{"title":"Remedy","contents":"<!--fragment#89287ac7f8#head-->Vanillare (바닐레어)<!--fragment#89287ac7f8#tail-->","link":"https://www.music-flo.com/detail/album/edzhiednh/albumtrack","retrieved":1634960420218,"image":"https://cdn.music-flo.com/image/v2/album/028/834/06/04/406834028_6171291a_s.jpg?1634806043202/dims/resize/140x140/quality/90"},{"title":"Yoyohere","contents":"<!--fragment#121eb40dbce#head-->Flatshop<!--fragment#121eb40dbce#tail-->","link":"https://www.music-flo.com/detail/album/edzhizild/albumtrack","retrieved":1634960420234,"image":"https://cdn.music-flo.com/image/v2/album/350/836/06/04/406836350_6172360d_s.jpg?1634874894836/dims/resize/140x140/quality/90"},{"title":"갈래","contents":"<!--fragment#966fc801c6#head-->다린<!--fragment#966fc801c6#tail-->","link":"https://www.music-flo.com/detail/album/edzhinlel/albumtrack","retrieved":1634895591215,"image":"https://cdn.music-flo.com/image/v2/album/545/832/06/04/406832545_61710ffb_o.jpg?1634799612533/dims/resize/140x140/quality/90"},{"title":"오직 그곳에서만 빛난다","contents":"<!--fragment#1577825c571#head-->투 데이 올드 스니커즈<!--fragment#1577825c571#tail-->","link":"https://www.music-flo.com/detail/album/edzhazzey/albumtrack","retrieved":1634960420099},{"title":"빛을 보낼게","contents":"<!--fragment#bffe900574#head-->OYEON (오연)<!--fragment#bffe900574#tail-->","link":"https://www.music-flo.com/detail/album/edzhnylae/albumtrack","retrieved":1634960420102},{"title":"끝이 다가온 걸 아는데","contents":"<!--fragment#ca111049b4#head-->신현우<!--fragment#ca111049b4#tail-->","link":"https://www.music-flo.com/detail/album/edzhionao/albumtrack","retrieved":1634960420102},{"title":"Shine","contents":"<!--fragment#62fd21f8ce#head-->Girls Planet 999<!--fragment#62fd21f8ce#tail-->","link":"https://www.music-flo.com/detail/album/edzhiahzo/albumtrack","retrieved":1634895591262},{"title":"서툰 사랑","contents":"<!--fragment#9a252f6c26#head-->비비안<!--fragment#9a252f6c26#tail-->","link":"https://www.music-flo.com/detail/album/edzhildil/albumtrack","retrieved":1634960420123},{"title":"Driver","contents":"<!--fragment#616e5d3259#head-->이어보이<!--fragment#616e5d3259#tail-->","link":"https://www.music-flo.com/detail/album/edzhidhha/albumtrack","retrieved":1634960420123},{"title":"Thank You with. JUNNY (MIC SWG LIVE VER)","contents":"<!--fragment#13f4b1612ae#head-->마이크스웨거 (MIC SWG)<!--fragment#13f4b1612ae#tail-->","link":"https://www.music-flo.com/detail/album/edzhnleye/albumtrack","retrieved":1634960420123},{"title":"Freaky (Feat. Chillin Homie)","contents":"<!--fragment#168cf095a6#head-->플루마 (PLUMA)<!--fragment#168cf095a6#tail-->","link":"https://www.music-flo.com/detail/album/edzhilyyn/albumtrack","retrieved":1634895591263},{"title":"처방전","contents":"<!--fragment#9f64a88cc4#head-->sogumm<!--fragment#9f64a88cc4#tail-->","link":"https://www.music-flo.com/detail/album/edzhayzie/albumtrack","retrieved":1634895591248},{"title":"Labyrinth (How can I) (feat. Kev)","contents":"<!--fragment#13a1559bbcd#head-->Rockett<!--fragment#13a1559bbcd#tail-->","link":"https://www.music-flo.com/detail/album/edzhnzdza/albumtrack","retrieved":1634960420132},{"title":"1022","contents":"<!--fragment#c38590ab7#head-->이한울<!--fragment#c38590ab7#tail-->","link":"https://www.music-flo.com/detail/album/edzhnlazy/albumtrack","retrieved":1634895591264},{"title":"Look at the Sky","contents":"<!--fragment#9d5aaf2127#head-->정엽<!--fragment#9d5aaf2127#tail-->","link":"https://www.music-flo.com/detail/album/edzhilyyi/albumtrack","retrieved":1634895591261},{"title":"Holiday","contents":"<!--fragment#e1713202d2#head-->제휘<!--fragment#e1713202d2#tail-->","link":"https://www.music-flo.com/detail/album/edzhiayhy/albumtrack","retrieved":1634895591190},{"title":"Welcome (Explicit Ver.)","contents":"<!--fragment#6e16cfb9#head-->XINSAYNE<!--fragment#6e16cfb9#tail-->","link":"https://www.music-flo.com/detail/album/edzhnedad/albumtrack","retrieved":1634960420134},{"title":"도미노","contents":"<!--fragment#96fa6cf73c#head-->나상현씨밴드<!--fragment#96fa6cf73c#tail-->","link":"https://www.music-flo.com/detail/album/edzhneden/albumtrack","retrieved":1634895591182},{"title":"Nightmare","contents":"<!--fragment#5af36ad1f9#head-->YEGNY (최예근)<!--fragment#5af36ad1f9#tail-->","link":"https://www.music-flo.com/detail/album/edzhnznhn/albumtrack","retrieved":1634895591182},{"title":"This is the Moment (지금 이 순간)","contents":"<!--fragment#ed78c85f01#head-->홍광호<!--fragment#ed78c85f01#tail-->","link":"https://www.music-flo.com/detail/album/edzhiieyy/albumtrack","retrieved":1634874040979},{"title":"I'm Sober","contents":"<!--fragment#104959ffe89#head-->달싸비 (Dalsabi)<!--fragment#104959ffe89#tail-->","link":"https://www.music-flo.com/detail/album/edzhnahon/albumtrack","retrieved":1634960420135},{"title":"가능성(feat. 김사월)","contents":"<!--fragment#e224e50a50#head-->브로콜리너마저<!--fragment#e224e50a50#tail-->","link":"https://www.music-flo.com/detail/album/edzhieale/albumtrack","retrieved":1634874040980},{"title":"Ma boo","contents":"<!--fragment#b935113c3#head-->동우석<!--fragment#b935113c3#tail-->","link":"https://www.music-flo.com/detail/album/edzhnedei/albumtrack","retrieved":1634874040978},{"title":"Givenchy","contents":"<!--fragment#c21e7423dc#head-->Jiho Givenchy (지호지방시)<!--fragment#c21e7423dc#tail-->","link":"https://www.music-flo.com/detail/album/edzhiiiyl/albumtrack","retrieved":1634895591194},{"title":"The Night With You","contents":"<!--fragment#4ba9974a8f#head-->한선화<!--fragment#4ba9974a8f#tail-->","link":"https://www.music-flo.com/detail/album/edzhnizno/albumtrack","retrieved":1634874040981},{"title":"That's True","contents":"<!--fragment#143848982fb#head-->Ohwon Lee (진짜사나이)<!--fragment#143848982fb#tail-->","link":"https://www.music-flo.com/detail/album/edzhindee/albumtrack","retrieved":1634895591190},{"title":"빠져버렸다","contents":"<!--fragment#e58acf54f6#head-->진 (JIN)<!--fragment#e58acf54f6#tail-->","link":"https://www.music-flo.com/detail/album/edzhnelen/albumtrack","retrieved":1634895591195},{"title":"휘파람","contents":"<!--fragment#165ccd1fae1#head-->대학부(김성준 &amp; 김희석 &amp; 유용민 &amp; 이주천)<!--fragment#165ccd1fae1#tail-->","link":"https://www.music-flo.com/detail/album/edzhienyh/albumtrack","retrieved":1634874040988},{"title":"아직도 난 (With. 명헌)","contents":"<!--fragment#8898989a26#head-->Milkyway<!--fragment#8898989a26#tail-->","link":"https://www.music-flo.com/detail/album/edzhnizay/albumtrack","retrieved":1634895591198},{"title":"Slow Starter (With 이승기)","contents":"<!--fragment#e9933ebbe3#head-->윤종신<!--fragment#e9933ebbe3#tail-->","link":"https://www.music-flo.com/detail/album/edzhaohdn/albumtrack","retrieved":1634809230873},{"title":"동네","contents":"<!--fragment#a5debcb480#head-->해빈<!--fragment#a5debcb480#tail-->","link":"https://www.music-flo.com/detail/album/edzhaeaez/albumtrack","retrieved":1634874040987},{"title":"Oh you","contents":"<!--fragment#110bd4f96d3#head-->리디아 (Lydia)<!--fragment#110bd4f96d3#tail-->","link":"https://www.music-flo.com/detail/album/edzhidiai/albumtrack","retrieved":1634874040940},{"title":"한사람","contents":"<!--fragment#9be4bcee0c#head-->향이<!--fragment#9be4bcee0c#tail-->","link":"https://www.music-flo.com/detail/album/edzhinaia/albumtrack","retrieved":1634874040938},{"title":"시간이 지나서 (feat. 죠지)","contents":"<!--fragment#58a8e67371#head-->Hiko<!--fragment#58a8e67371#tail-->","link":"https://www.music-flo.com/detail/album/edzhnyela/albumtrack","retrieved":1634874040936},{"title":"지금 뭐해","contents":"<!--fragment#c4266fe8c1#head-->벤<!--fragment#c4266fe8c1#tail-->","link":"https://www.music-flo.com/detail/album/edzhnihah/albumtrack","retrieved":1634809230874},{"title":"Alone (Feat. GSoul)","contents":"<!--fragment#50762f4b2b#head-->정키 (Jung Key)<!--fragment#50762f4b2b#tail-->","link":"https://www.music-flo.com/detail/album/edzhnennl/albumtrack","retrieved":1634809230875},{"title":"빛을 향해 가보자","contents":"<!--fragment#e02fd1b6f5#head-->Ella J (엘라제이)<!--fragment#e02fd1b6f5#tail-->","link":"https://www.music-flo.com/detail/album/edzhnyaoy/albumtrack","retrieved":1634874040937},{"title":"넌 사랑을 모른다 했지(티파니에서 모닝 키스를 OST)","contents":"<!--fragment#19da4529f3#head-->진영<!--fragment#19da4529f3#tail-->","link":"https://www.music-flo.com/detail/album/edzoyeeza/albumtrack","retrieved":1634809230876},{"title":"Our Blue (아는 여자애 X CHEEZE (치즈))","contents":"<!--fragment#135a6707ecf#head-->CHEEZE (치즈)<!--fragment#135a6707ecf#tail-->","link":"https://www.music-flo.com/detail/album/edzhaiayd/albumtrack","retrieved":1634809230878},{"title":"우리란 게 없었던 그때로","contents":"<!--fragment#ac4cf98b88#head-->지예홍<!--fragment#ac4cf98b88#tail-->","link":"https://www.music-flo.com/detail/album/edzhnyeyz/albumtrack","retrieved":1634874040942},{"title":"아침","contents":"<!--fragment#155b515824#head-->마인드유<!--fragment#155b515824#tail-->","link":"https://www.music-flo.com/detail/album/edzhnlizy/albumtrack","retrieved":1634809230876},{"title":"The Moment","contents":"<!--fragment#fdb95c22cb#head-->김예림 (Lim Kim)<!--fragment#fdb95c22cb#tail-->","link":"https://www.music-flo.com/detail/album/edzhnldoo/albumtrack","retrieved":1634809230878},{"title":"열두시반 (Feat. CHEEZE)","contents":"<!--fragment#9c8dde1e2f#head-->Kvsh (캐시)<!--fragment#9c8dde1e2f#tail-->","link":"https://www.music-flo.com/detail/album/edzhnlznd/albumtrack","retrieved":1634809230783},{"title":"원심력","contents":"<!--fragment#4d0c3cbd9e#head-->워커 (Walker)<!--fragment#4d0c3cbd9e#tail-->","link":"https://www.music-flo.com/detail/album/edzhahyhl/albumtrack","retrieved":1634874040944},{"title":"Black Crown","contents":"<!--fragment#15be0908389#head-->KINGDOM(킹덤)<!--fragment#15be0908389#tail-->","link":"https://www.music-flo.com/detail/album/edzhiaoea/albumtrack","retrieved":1634809230782},{"title":"excuses","contents":"<!--fragment#117c9c9ba0a#head-->G. Nine<!--fragment#117c9c9ba0a#tail-->","link":"https://www.music-flo.com/detail/album/edzhazlhi/albumtrack","retrieved":1634809230796},{"title":"Indigo","contents":"<!--fragment#f9db886aa4#head-->이봄<!--fragment#f9db886aa4#tail-->","link":"https://www.music-flo.com/detail/album/edzhnedzy/albumtrack","retrieved":1634809230790},{"title":"해피엔딩","contents":"<!--fragment#cb1c5b46e9#head-->이정권<!--fragment#cb1c5b46e9#tail-->","link":"https://www.music-flo.com/detail/album/edzhndani/albumtrack","retrieved":1634787633761},{"title":"모르겠어요","contents":"<!--fragment#148a7b0fa3a#head-->장들레<!--fragment#148a7b0fa3a#tail-->","link":"https://www.music-flo.com/detail/album/edzhnilzd/albumtrack","retrieved":1634787633746},{"title":"가와사키 닌자","contents":"<!--fragment#9c28498d6c#head-->Zayvo (제이보)<!--fragment#9c28498d6c#tail-->","link":"https://www.music-flo.com/detail/album/edzzieddi/albumtrack","retrieved":1634809230789},{"title":"BMX (ft. Osshun Gum) (prod. Festy Wxs)","contents":"<!--fragment#608a4109ac#head-->Kim Addict (킴 애딕)<!--fragment#608a4109ac#tail-->","link":"https://www.music-flo.com/detail/album/edzhnizny/albumtrack","retrieved":1634809230789},{"title":"이럴거면","contents":"<!--fragment#144c1bd889b#head-->임상현<!--fragment#144c1bd889b#tail-->","link":"https://www.music-flo.com/detail/album/edzhaialo/albumtrack","retrieved":1634787633687},{"title":"Hide and Seek","contents":"<!--fragment#2c6c16440#head-->문수진 (Moon Sujin)<!--fragment#2c6c16440#tail-->","link":"https://www.music-flo.com/detail/album/edzhahyoh/albumtrack","retrieved":1634787633763},{"title":"be","contents":"<!--fragment#172589274dd#head-->은혁 (EUNHYUK)<!--fragment#172589274dd#tail-->","link":"https://www.music-flo.com/detail/album/edzhaydii/albumtrack","retrieved":1634722808699},{"title":"SEADANCE (Feat. 야누 (YANU))","contents":"<!--fragment#7456fa231d#head-->Chamelego<!--fragment#7456fa231d#tail-->","link":"https://www.music-flo.com/detail/album/edzhaodyl/albumtrack","retrieved":1634809230806},{"title":"심연","contents":"<!--fragment#10ecd0d8bc8#head-->도우 (DOU)<!--fragment#10ecd0d8bc8#tail-->","link":"https://www.music-flo.com/detail/album/edzoyhehn/albumtrack","retrieved":1634809230807},{"title":"12.19km (Solo ver.)","contents":"<!--fragment#74e2a24791#head-->지진석<!--fragment#74e2a24791#tail-->","link":"https://www.music-flo.com/detail/album/edzhneoll/albumtrack","retrieved":1634787633661},{"title":"너의 곁엔 내가 나의 곁엔 네가 (Feat. 모닝커피 (Morning Coffee))","contents":"<!--fragment#14f37c92d39#head-->브런치 레시피 (Brunch recipe)<!--fragment#14f37c92d39#tail-->","link":"https://www.music-flo.com/detail/album/edzhnieel/albumtrack","retrieved":1634787633661},{"title":"U Hoo Hoo","contents":"<!--fragment#13268b00b2a#head-->클랑 (KLANG)<!--fragment#13268b00b2a#tail-->","link":"https://www.music-flo.com/detail/album/edzhnldly/albumtrack","retrieved":1634787633681},{"title":"Why","contents":"<!--fragment#13606866158#head-->heyden<!--fragment#13606866158#tail-->","link":"https://www.music-flo.com/detail/album/edzohodea/albumtrack","retrieved":1634787633679},{"title":"밤노래","contents":"<!--fragment#6ad4f9bbcf#head-->형태<!--fragment#6ad4f9bbcf#tail-->","link":"https://www.music-flo.com/detail/album/edzhnilha/albumtrack","retrieved":1634787633766},{"title":"싹둑 (Love Cut)","contents":"<!--fragment#165bd3e371f#head-->CNBLUE (씨엔블루)<!--fragment#165bd3e371f#tail-->","link":"https://www.music-flo.com/detail/album/edzhaydzd/albumtrack","retrieved":1634722808702},{"title":"나의 세계는","contents":"<!--fragment#1a8bac9511#head-->한희정<!--fragment#1a8bac9511#tail-->","link":"https://www.music-flo.com/detail/album/edzhazheo/albumtrack","retrieved":1634787633775},{"title":"그래도 사랑이었잖아","contents":"<!--fragment#30684b4537#head-->거미<!--fragment#30684b4537#tail-->","link":"https://www.music-flo.com/detail/album/edzhayioo/albumtrack","retrieved":1634722808701},{"title":"왈칵","contents":"<!--fragment#15920d1765d#head-->락다이아몬드<!--fragment#15920d1765d#tail-->","link":"https://www.music-flo.com/detail/album/edzhnaadi/albumtrack","retrieved":1634787633686},{"title":"어디있나요","contents":"<!--fragment#121a8009c0c#head-->김재희<!--fragment#121a8009c0c#tail-->","link":"https://www.music-flo.com/detail/album/edzhnihae/albumtrack","retrieved":1634787633692},{"title":"여전히 영원히","contents":"<!--fragment#b32cdd2afa#head-->XIA (준수)<!--fragment#b32cdd2afa#tail-->","link":"https://www.music-flo.com/detail/album/edzhndzdn/albumtrack","retrieved":1634722808701},{"title":"안녕 오랜 내 사랑","contents":"<!--fragment#3d15279b9b#head-->NeD (네드)<!--fragment#3d15279b9b#tail-->","link":"https://www.music-flo.com/detail/album/edzhnioal/albumtrack","retrieved":1634787633683},{"title":"Tie a Cherry","contents":"<!--fragment#cb24796320#head-->CL<!--fragment#cb24796320#tail-->","link":"https://www.music-flo.com/detail/album/edzoiizad/albumtrack","retrieved":1634705362176},{"title":"붉은 노을 (Live Ver.)","contents":"<!--fragment#1d24c33baa#head-->신촌 블루스<!--fragment#1d24c33baa#tail-->","link":"https://www.music-flo.com/detail/album/edzhdeihi/albumtrack","retrieved":1634787633690},{"title":"창가","contents":"<!--fragment#11a96595e57#head-->나을<!--fragment#11a96595e57#tail-->","link":"https://www.music-flo.com/detail/album/edzhnindz/albumtrack","retrieved":1634787633693},{"title":"MBT","contents":"<!--fragment#b6bc0eb9f5#head-->허성현 (Huh!)<!--fragment#b6bc0eb9f5#tail-->","link":"https://www.music-flo.com/detail/album/edzhaidaz/albumtrack","retrieved":1634722808702},{"title":"요 (夭)","contents":"<!--fragment#45ec4086e3#head-->팎 (PAKK)<!--fragment#45ec4086e3#tail-->","link":"https://www.music-flo.com/detail/album/edzhazhne/albumtrack","retrieved":1634787633700},{"title":"비 투성이","contents":"<!--fragment#c749446ea0#head-->The Hills (더 힐스)<!--fragment#c749446ea0#tail-->","link":"https://www.music-flo.com/detail/album/edzhaehih/albumtrack","retrieved":1634787633697},{"title":"사랑의 형태 (feat. oceanfromtheblue)","contents":"<!--fragment#1460b4dabec#head-->서자영<!--fragment#1460b4dabec#tail-->","link":"https://www.music-flo.com/detail/album/edzhndzza/albumtrack","retrieved":1634722808703},{"title":"SUNSHINE LOVE(2021) (Feat. SE O (세오))","contents":"<!--fragment#162b79efe83#head-->스텐<!--fragment#162b79efe83#tail-->","link":"https://www.music-flo.com/detail/album/edzhaiahn/albumtrack","retrieved":1634722808645},{"title":"아이러니즘 (Live)","contents":"<!--fragment#445708ec6f#head-->위댄스<!--fragment#445708ec6f#tail-->","link":"https://www.music-flo.com/detail/album/edzhndaoa/albumtrack","retrieved":1634787633705},{"title":"Mindset","contents":"<!--fragment#de08a7efaf#head-->uju (우주)<!--fragment#de08a7efaf#tail-->","link":"https://www.music-flo.com/detail/album/edzhazyii/albumtrack","retrieved":1634722808638},{"title":"No Problem (mom′s call)","contents":"<!--fragment#4775655c72#head-->키밤 (KEEBOMB)<!--fragment#4775655c72#tail-->","link":"https://www.music-flo.com/detail/album/edzhahziz/albumtrack","retrieved":1634701240268},{"title":"Hyper Beam","contents":"<!--fragment#6ab88c6310#head-->제리황<!--fragment#6ab88c6310#tail-->","link":"https://www.music-flo.com/detail/album/edzhazhia/albumtrack","retrieved":1634722808619},{"title":"ISLAND(Dokdo, Beautiful Island of Korea)","contents":"<!--fragment#1534462f3a5#head-->이소정<!--fragment#1534462f3a5#tail-->","link":"https://www.music-flo.com/detail/album/edzhahyoy/albumtrack","retrieved":1634701240299},{"title":"Dear","contents":"<!--fragment#d108beecb1#head-->운찬<!--fragment#d108beecb1#tail-->","link":"https://www.music-flo.com/detail/album/edzhaienh/albumtrack","retrieved":1634722808646},{"title":"무한대","contents":"<!--fragment#58383e4f7e#head-->SUMIN (수민)<!--fragment#58383e4f7e#tail-->","link":"https://www.music-flo.com/detail/album/edzhaided/albumtrack","retrieved":1634701240193},{"title":"FADE OUT (Feat. SHIRT)","contents":"<!--fragment#14aba4915a6#head-->Chan<!--fragment#14aba4915a6#tail-->","link":"https://www.music-flo.com/detail/album/edzhayndz/albumtrack","retrieved":1634701240303},{"title":"Alright","contents":"<!--fragment#90735a2e58#head-->범키<!--fragment#90735a2e58#tail-->","link":"https://www.music-flo.com/detail/album/edzhaonyi/albumtrack","retrieved":1634701240293},{"title":"어서오세요 (Feat. 이창민 Of 2AM)","contents":"<!--fragment#40f2efe904#head-->후니용이<!--fragment#40f2efe904#tail-->","link":"https://www.music-flo.com/detail/album/edzhayony/albumtrack","retrieved":1634701240204},{"title":"냉정과 열정 사이","contents":"<!--fragment#14f911ac96f#head-->남우현<!--fragment#14f911ac96f#tail-->","link":"https://www.music-flo.com/detail/album/edzhazzno/albumtrack","retrieved":1634636414996},{"title":"구애","contents":"<!--fragment#9b440fa1cb#head-->Gila (길라)<!--fragment#9b440fa1cb#tail-->","link":"https://www.music-flo.com/detail/album/edzhazzeh/albumtrack","retrieved":1634701240192},{"title":"쑥스러운 고백 (Feat. 허니애플)","contents":"<!--fragment#15734ac4f12#head-->어반폴리<!--fragment#15734ac4f12#tail-->","link":"https://www.music-flo.com/detail/album/edzhaonho/albumtrack","retrieved":1634701240213},{"title":"BED","contents":"<!--fragment#a5d9053ea#head-->DEUL<!--fragment#a5d9053ea#tail-->","link":"https://www.music-flo.com/detail/album/edzhanhze/albumtrack","retrieved":1634701240304},{"title":"그녀의 노래","contents":"<!--fragment#b0fc206be1#head-->김페리<!--fragment#b0fc206be1#tail-->","link":"https://www.music-flo.com/detail/album/edzoynnhn/albumtrack","retrieved":1634701240213},{"title":"세이렌 (Seiren)","contents":"<!--fragment#5a4aaa0ef1#head-->세이렌 (Seiren)<!--fragment#5a4aaa0ef1#tail-->","link":"https://www.music-flo.com/detail/album/edzhalazy/albumtrack","retrieved":1634701240203},{"title":"싸구려 커피","contents":"<!--fragment#db65af937b#head-->해음<!--fragment#db65af937b#tail-->","link":"https://www.music-flo.com/detail/album/edzhayyzn/albumtrack","retrieved":1634701240299},{"title":"My Vibe (Ft. Jordyn Kane)","contents":"<!--fragment#13c3d3a85a#head-->Vandal Rock<!--fragment#13c3d3a85a#tail-->","link":"https://www.music-flo.com/detail/album/edzhanlih/albumtrack","retrieved":1634701240195},{"title":"마천루 (Feat. JUSTHIS)","contents":"<!--fragment#123e0e8942#head-->DON MALIK (던말릭)<!--fragment#123e0e8942#tail-->","link":"https://www.music-flo.com/detail/album/edzhazzlo/albumtrack","retrieved":1634636414999},{"title":"사진 (하늘만 바라봐)","contents":"<!--fragment#c7d746984e#head-->San E<!--fragment#c7d746984e#tail-->","link":"https://www.music-flo.com/detail/album/edzhaoaio/albumtrack","retrieved":1634636414995}]}