{"title":"FLO ─ New Track","url":"https://www.music-flo.com/new/track?sortType=KPOP","favicon":"https://www.music-flo.com/favicon.ico","elements":[{"contents":"<!--fragment#4bee34ee08#head--> 강다니엘 <!--fragment#4bee34ee08#tail-->","retrieved":1637070026680,"image":"https://cdn.music-flo.com/image/v2/album/000/982/06/04/406982000_61932d8b_o.jpg?1637035405445/dims/resize/140x140/quality/90"},{"contents":"<!--fragment#5ed560255f#head--> 윤하 <!--fragment#5ed560255f#tail-->","retrieved":1637070026681,"image":"https://cdn.music-flo.com/image/v2/album/287/981/06/04/406981287_619302ef_s.jpg?1637024498087/dims/resize/140x140/quality/90"},{"contents":"<!--fragment#dc704c9367#head--> GEMINI (제미나이) <!--fragment#dc704c9367#tail-->","retrieved":1637070026681,"image":"https://cdn.music-flo.com/image/v2/album/010/974/06/04/406974010_618e2038_o.jpg?1636704313537/dims/resize/140x140/quality/90"},{"contents":"<!--fragment#a0b567bcc#head--> 적재 <!--fragment#a0b567bcc#tail-->","retrieved":1637070026682,"image":"https://cdn.music-flo.com/image/v2/album/737/978/06/04/406978737_619233b5_s.jpg?1636971447770/dims/resize/140x140/quality/90"},{"contents":"<!--fragment#15dc47a5671#head--> 저스디스 (JUSTHIS) <!--fragment#15dc47a5671#tail-->","retrieved":1637070026683,"image":"https://cdn.music-flo.com/image/v2/album/288/981/06/04/406981288_619302ef_s.jpg?1637024496635/dims/resize/140x140/quality/90"},{"contents":"<!--fragment#1357b11e644#head--> 김미정 <!--fragment#1357b11e644#tail-->","retrieved":1637070026684,"image":"https://cdn.music-flo.com/image/v2/album/678/981/06/04/406981678_61931498_o.jpg?1637029017381/dims/resize/140x140/quality/90"},{"contents":"<!--fragment#1719af855ed#head--> 전남친 <!--fragment#1719af855ed#tail-->","retrieved":1637070026684,"image":"https://cdn.music-flo.com/image/v2/album/258/977/06/04/406977258_6190d0c9_o.jpg?1636880586151/dims/resize/140x140/quality/90"},{"contents":"<!--fragment#1d5e412b94#head--> 차우 (Chawoo) <!--fragment#1d5e412b94#tail-->","retrieved":1637070026620},{"contents":"<!--fragment#15027b17a27#head--> 신주현 <!--fragment#15027b17a27#tail-->","retrieved":1637070026622},{"contents":"<!--fragment#80fd1bebca#head--> sEODo <!--fragment#80fd1bebca#tail-->","retrieved":1637070026622},{"contents":"<!--fragment#14f6efdb736#head--> Neidi (네이디) <!--fragment#14f6efdb736#tail-->","retrieved":1637070026623},{"contents":"<!--fragment#2bc547f394#head--> SUL (에슈엘) <!--fragment#2bc547f394#tail-->","retrieved":1637070026623},{"contents":"<!--fragment#1ed8ce17b0#head--> 015B <!--fragment#1ed8ce17b0#tail-->","retrieved":1637070026624},{"contents":"<!--fragment#64888bfbe7#head--> 해윤 (체리블렛) <!--fragment#64888bfbe7#tail-->","retrieved":1637070026625},{"contents":"<!--fragment#11d287fce07#head--> 정해일 <!--fragment#11d287fce07#tail-->","retrieved":1637070026626},{"contents":"<!--fragment#5831c6c489#head--> 해이 <!--fragment#5831c6c489#tail-->","retrieved":1637070026626},{"contents":"<!--fragment#13a999b271#head--> 두번째 별 <!--fragment#13a999b271#tail-->","retrieved":1637070026627},{"contents":"<!--fragment#2f9522579b#head--> 찬현 <!--fragment#2f9522579b#tail-->","retrieved":1637070026628},{"contents":"<!--fragment#154bac69e96#head--> 티아라 (T-ara) <!--fragment#154bac69e96#tail-->","retrieved":1637070026629},{"contents":"<!--fragment#158ab74022d#head--> Jimmy Brown <!--fragment#158ab74022d#tail-->","retrieved":1637070026630},{"contents":"<!--fragment#8f0b6d2f84#head--> Kohway <!--fragment#8f0b6d2f84#tail-->","retrieved":1637070026631},{"contents":"<!--fragment#d5b10880a0#head--> 화아 (HwA) <!--fragment#d5b10880a0#tail-->","retrieved":1637070026632},{"contents":"<!--fragment#6e92d14bf#head--> 소년:달 <!--fragment#6e92d14bf#tail-->","retrieved":1637070026633},{"contents":"<!--fragment#ed04f62673#head--> 이동윤 <!--fragment#ed04f62673#tail-->","retrieved":1637070026634},{"contents":"<!--fragment#3a54ccb70d#head--> SWAY (스웨이) <!--fragment#3a54ccb70d#tail-->","retrieved":1637070026635},{"contents":"<!--fragment#1054dd3a769#head--> shinsammy sj <!--fragment#1054dd3a769#tail-->","retrieved":1637070026636},{"contents":"<!--fragment#fdf3df3069#head--> Robiq <!--fragment#fdf3df3069#tail-->","retrieved":1637070026637},{"contents":"<!--fragment#2cdcc4ea6a#head--> 섬머 <!--fragment#2cdcc4ea6a#tail-->","retrieved":1637070026638},{"contents":"<!--fragment#b1e2ba5e3a#head--> 투 데이 올드 스니커즈 <!--fragment#b1e2ba5e3a#tail-->","retrieved":1637070026639},{"contents":"<!--fragment#1546561b6db#head--> Dalmood <!--fragment#1546561b6db#tail-->","retrieved":1637070026640},{"contents":"<!--fragment#1011ca28981#head--> 허각 <!--fragment#1011ca28981#tail-->","retrieved":1637070026641},{"contents":"<!--fragment#a8e850d150#head--> 버나드 박 <!--fragment#a8e850d150#tail-->","retrieved":1637070026643},{"contents":"<!--fragment#1081797d3c4#head--> 장덕철 <!--fragment#1081797d3c4#tail-->","retrieved":1637070026644},{"contents":"<!--fragment#15d039ec009#head--> 코튼캔디 (Cotton Candy) <!--fragment#15d039ec009#tail-->","retrieved":1637070026645},{"contents":"<!--fragment#4801cfdbe#head--> 손태진 <!--fragment#4801cfdbe#tail-->","retrieved":1637070026646},{"contents":"<!--fragment#16cd8ff6902#head--> 다비 (DAVII) <!--fragment#16cd8ff6902#tail-->","retrieved":1637070026647},{"contents":"<!--fragment#bc1671827c#head--> 김우진 <!--fragment#bc1671827c#tail-->","retrieved":1637070026648},{"contents":"<!--fragment#14af94c0685#head--> JJK <!--fragment#14af94c0685#tail-->","retrieved":1637070026648},{"contents":"<!--fragment#d1ab2c69f0#head--> GYU HYUK <!--fragment#d1ab2c69f0#tail-->","retrieved":1637070026649},{"contents":"<!--fragment#101f706770a#head--> 모모랜드 (MOMOLAND) <!--fragment#101f706770a#tail-->","retrieved":1637070026650},{"contents":"<!--fragment#17a1e0dff1e#head--> 권채린 <!--fragment#17a1e0dff1e#tail-->","retrieved":1637070026651},{"contents":"<!--fragment#ce1dca422d#head--> 소희 <!--fragment#ce1dca422d#tail-->","retrieved":1637070026652},{"contents":"<!--fragment#645daa682e#head--> 스트레이 (The Stray) <!--fragment#645daa682e#tail-->","retrieved":1637070026653},{"contents":"<!--fragment#faa6b46ef#head--> Paper ℃up (페이퍼컵) <!--fragment#faa6b46ef#tail-->","retrieved":1637070026654},{"contents":"<!--fragment#e0facb7ecf#head--> YoBoy (강요셉) <!--fragment#e0facb7ecf#tail-->","retrieved":1637070026655},{"contents":"<!--fragment#db62079585#head--> 이하이 <!--fragment#db62079585#tail-->","retrieved":1637070026655},{"contents":"<!--fragment#bb9162395e#head--> 이소라 <!--fragment#bb9162395e#tail-->","retrieved":1637070026656},{"contents":"<!--fragment#4a9aa9d1a6#head--> 유하정 <!--fragment#4a9aa9d1a6#tail-->","retrieved":1637070026668},{"contents":"<!--fragment#178c7ef538f#head--> 오반 (OVAN) <!--fragment#178c7ef538f#tail-->","retrieved":1637070026669},{"contents":"<!--fragment#30770f8b24#head--> ZASMIIN (자스민) <!--fragment#30770f8b24#tail-->","retrieved":1637070026670},{"contents":"<!--fragment#f9ce9e37fe#head--> 마이크스웨거 (MIC SWG) <!--fragment#f9ce9e37fe#tail-->","retrieved":1637070026671},{"contents":"<!--fragment#a6073d85c0#head--> 차가을 <!--fragment#a6073d85c0#tail-->","retrieved":1637070026672},{"contents":"<!--fragment#94d9f8ec0f#head--> 요요미 <!--fragment#94d9f8ec0f#tail-->","retrieved":1637070026673},{"contents":"<!--fragment#12e14e96aff#head--> BADROOM <!--fragment#12e14e96aff#tail-->","retrieved":1637070026675},{"contents":"<!--fragment#e504f6c5be#head--> 1day of the week <!--fragment#e504f6c5be#tail-->","retrieved":1637070026675},{"contents":"<!--fragment#4dcba64ff9#head--> 양지은 <!--fragment#4dcba64ff9#tail-->","retrieved":1637070026676},{"contents":"<!--fragment#13185c1f7da#head--> 한경일 <!--fragment#13185c1f7da#tail-->","retrieved":1637070026677},{"contents":"<!--fragment#9462c59c51#head--> 뮤진 (MUZIN) <!--fragment#9462c59c51#tail-->","retrieved":1637070026678},{"contents":"<!--fragment#c56504923e#head--> King Bart <!--fragment#c56504923e#tail-->","retrieved":1637070026679},{"contents":"<!--fragment#7dc88c0392#head--> SURL (설) <!--fragment#7dc88c0392#tail-->","retrieved":1637070026679},{"contents":"<!--fragment#36dc3b3941#head--> 코다 브릿지 <!--fragment#36dc3b3941#tail-->","retrieved":1637070026685},{"contents":"<!--fragment#12f2036a1fa#head--> 라디 (Ra. D) <!--fragment#12f2036a1fa#tail-->","retrieved":1637070026685},{"contents":"<!--fragment#841c07fae9#head--> 차원 (CHAWON) <!--fragment#841c07fae9#tail-->","retrieved":1637070026686},{"contents":"<!--fragment#10d0f6825af#head--> 배현이 <!--fragment#10d0f6825af#tail-->","retrieved":1637070026687},{"contents":"<!--fragment#4bb0321e6e#head--> 멜로틱 <!--fragment#4bb0321e6e#tail-->","retrieved":1637070026687},{"contents":"<!--fragment#1348230797f#head--> yovng trucker <!--fragment#1348230797f#tail-->","retrieved":1637070026690},{"contents":"<!--fragment#67f200f94a#head--> 123 <!--fragment#67f200f94a#tail-->","retrieved":1637070026693},{"contents":"<!--fragment#12a1e8e81d2#head--> 정동호 <!--fragment#12a1e8e81d2#tail-->","retrieved":1637070026693},{"contents":"<!--fragment#117c9675e4#head--> ATLET <!--fragment#117c9675e4#tail-->","retrieved":1637070026694},{"contents":"<!--fragment#2f1a6ee504#head--> MINGYU <!--fragment#2f1a6ee504#tail-->","retrieved":1637070026695},{"contents":"<!--fragment#7c61d3103e#head--> 탑현 <!--fragment#7c61d3103e#tail-->","retrieved":1637070026696},{"contents":"<!--fragment#9b24d9d24b#head--> 전채언 <!--fragment#9b24d9d24b#tail-->","retrieved":1637070026696},{"contents":"<!--fragment#f7f5939d15#head--> 그_냥 <!--fragment#f7f5939d15#tail-->","retrieved":1637070026697},{"contents":"<!--fragment#ee929d5fa8#head--> 종코 <!--fragment#ee929d5fa8#tail-->","retrieved":1637070026698},{"contents":"<!--fragment#d157d8c0cd#head--> yey <!--fragment#d157d8c0cd#tail-->","retrieved":1637070026698},{"contents":"<!--fragment#8245279f4f#head--> GongGongGoo009 <!--fragment#8245279f4f#tail-->","retrieved":1637070026699},{"contents":"<!--fragment#176508f4dda#head--> 래원 (Layone) <!--fragment#176508f4dda#tail-->","retrieved":1637070026700},{"contents":"<!--fragment#bdcf2dcaa2#head--> Sneezy <!--fragment#bdcf2dcaa2#tail-->","retrieved":1637070026700},{"contents":"<!--fragment#1b10962c03#head--> 쥰키 <!--fragment#1b10962c03#tail-->","retrieved":1637070026712},{"contents":"<!--fragment#15f7ce7e073#head--> 신지후 <!--fragment#15f7ce7e073#tail-->","retrieved":1637070026712},{"contents":"<!--fragment#40cbefb970#head--> 홍대광 <!--fragment#40cbefb970#tail-->","retrieved":1637070026712},{"contents":"<!--fragment#12540eb4010#head--> 요한 <!--fragment#12540eb4010#tail-->","retrieved":1637070026712},{"contents":"<!--fragment#62082d8bc5#head--> 조항조 <!--fragment#62082d8bc5#tail-->","retrieved":1637070026713},{"contents":"<!--fragment#1548cd5e727#head--> sokodomo <!--fragment#1548cd5e727#tail-->","retrieved":1637070026714},{"contents":"<!--fragment#b2649e5721#head--> 이영현 <!--fragment#b2649e5721#tail-->","retrieved":1637070026716},{"contents":"<!--fragment#108bf5ef2f2#head--> 김승주 <!--fragment#108bf5ef2f2#tail-->","retrieved":1637070026717},{"contents":"<!--fragment#8a252927be#head--> KLAZY (크레이지) <!--fragment#8a252927be#tail-->","retrieved":1637070026717},{"contents":"<!--fragment#b80c4c36d7#head--> 승준 <!--fragment#b80c4c36d7#tail-->","retrieved":1637070026718},{"contents":"<!--fragment#12c899800f9#head--> 제이문 (Jay Moon) <!--fragment#12c899800f9#tail-->","retrieved":1637070026718},{"contents":"<!--fragment#6340d17809#head--> Sweet The Kid <!--fragment#6340d17809#tail-->","retrieved":1637070026719},{"contents":"<!--fragment#c46351dd1c#head--> 앤드유 <!--fragment#c46351dd1c#tail-->","retrieved":1637070026719},{"contents":"<!--fragment#5414e0e2e5#head--> TWICE (트와이스) <!--fragment#5414e0e2e5#tail-->","retrieved":1637070026721},{"contents":"<!--fragment#c87181ba66#head--> pH-1 <!--fragment#c87181ba66#tail-->","retrieved":1637070026723},{"contents":"<!--fragment#152d15ebd9d#head--> 더 브릿지 (The Bridge) <!--fragment#152d15ebd9d#tail-->","retrieved":1637070026723},{"contents":"<!--fragment#260a951190#head--> 공세영 <!--fragment#260a951190#tail-->","retrieved":1637070026724},{"contents":"<!--fragment#ee97a0e6f2#head--> 강효준 <!--fragment#ee97a0e6f2#tail-->","retrieved":1637070026725},{"contents":"<!--fragment#e5a13366d3#head--> DooBoo <!--fragment#e5a13366d3#tail-->","retrieved":1637070026726},{"contents":"<!--fragment#d4c38ffbdc#head--> Lrud (러드) <!--fragment#d4c38ffbdc#tail-->","retrieved":1637070026726},{"contents":"<!--fragment#6de30ef96#head--> 카코포니 (cacophony) <!--fragment#6de30ef96#tail-->","retrieved":1637070026727},{"contents":"<!--fragment#17418328208#head--> 그리 (GREE) <!--fragment#17418328208#tail-->","retrieved":1637070026728}]}