{"title":"FLO ─ New Track","url":"https://www.music-flo.com/new/track?sortType=KPOP","favicon":"https://www.music-flo.com/favicon.ico","elements":[{"contents":"<!--fragment#77a75fa30b#head--> B.I <!--fragment#77a75fa30b#tail-->","retrieved":1636630587408,"image":"https://cdn.music-flo.com/image/v2/album/655/966/06/04/406966655_618b728a_s.jpg?1636528781564/dims/resize/140x140/quality/90"},{"contents":"<!--fragment#ce5dd32252#head--> 창모 (CHANGMO) <!--fragment#ce5dd32252#tail-->","retrieved":1636630587408,"image":"https://cdn.music-flo.com/image/v2/album/666/966/06/04/406966666_618b7468_s.jpg?1636529258917/dims/resize/140x140/quality/90"},{"contents":"<!--fragment#14a4c5e4d01#head--> 10CM <!--fragment#14a4c5e4d01#tail-->","retrieved":1636630587428,"image":"https://cdn.music-flo.com/image/v2/album/684/966/06/04/406966684_618b7591_s.jpg?1636529555440/dims/resize/140x140/quality/90"},{"contents":"<!--fragment#69bc794d9#head--> DRIPPIN (드리핀) <!--fragment#69bc794d9#tail-->","retrieved":1636630587428,"image":"https://cdn.music-flo.com/image/v2/album/477/971/06/04/406971477_618c78c4_s.jpg?1636595911194/dims/resize/140x140/quality/90"},{"contents":"<!--fragment#acb3f7989c#head--> 알레프 (ALEPH) <!--fragment#acb3f7989c#tail-->","retrieved":1636630587429,"image":"https://cdn.music-flo.com/image/v2/album/599/961/06/04/406961599_6189cf1e_o.jpg?1636421407441/dims/resize/140x140/quality/90"},{"contents":"<!--fragment#5e5b88f280#head--> 김희재 <!--fragment#5e5b88f280#tail-->","retrieved":1636630587431,"image":"https://cdn.music-flo.com/image/v2/album/541/966/06/04/406966541_618b5f4a_o.jpg?1636523851831/dims/resize/140x140/quality/90"},{"contents":"<!--fragment#4a65c067fe#head--> 이혁 <!--fragment#4a65c067fe#tail-->","retrieved":1636630587434,"image":"https://cdn.music-flo.com/image/v2/album/748/964/06/04/406964748_618acc09_o.jpg?1636486153676/dims/resize/140x140/quality/90"},{"contents":"<!--fragment#d73bbeea14#head--> 안경잽이 <!--fragment#d73bbeea14#tail-->","retrieved":1636630587379},{"contents":"<!--fragment#178dac25dd2#head--> lilli lilli (릴리릴리) <!--fragment#178dac25dd2#tail-->","retrieved":1636630587379},{"contents":"<!--fragment#5cf7f2d8d7#head--> 그네 <!--fragment#5cf7f2d8d7#tail-->","retrieved":1636630587379},{"contents":"<!--fragment#d296d0c9f7#head--> GGM Kimbo <!--fragment#d296d0c9f7#tail-->","retrieved":1636630587379},{"contents":"<!--fragment#37c019f734#head--> 솔희 (SOHLHEE) <!--fragment#37c019f734#tail-->","retrieved":1636630587379},{"contents":"<!--fragment#9cddb55416#head--> 요아리 <!--fragment#9cddb55416#tail-->","retrieved":1636630587387},{"contents":"<!--fragment#d29c90e668#head--> 리오 (RIO) <!--fragment#d29c90e668#tail-->","retrieved":1636630587387},{"contents":"<!--fragment#d1edae28a9#head--> Midas P <!--fragment#d1edae28a9#tail-->","retrieved":1636630587387},{"contents":"<!--fragment#1117442ee#head--> ICHILLIN' (아이칠린) <!--fragment#1117442ee#tail-->","retrieved":1636630587387},{"contents":"<!--fragment#d438573c09#head--> 미란이 (Mirani) <!--fragment#d438573c09#tail-->","retrieved":1636630587387},{"contents":"<!--fragment#3de21312d2#head--> James Son <!--fragment#3de21312d2#tail-->","retrieved":1636630587387},{"contents":"<!--fragment#3dbcf688cb#head--> 양다일 <!--fragment#3dbcf688cb#tail-->","retrieved":1636630587387},{"contents":"<!--fragment#fe52969e65#head--> B1A4 <!--fragment#fe52969e65#tail-->","retrieved":1636630587387},{"contents":"<!--fragment#8055516c97#head--> 라임어택 <!--fragment#8055516c97#tail-->","retrieved":1636630587387},{"contents":"<!--fragment#ecb11c6c17#head--> PITTA (강형호) <!--fragment#ecb11c6c17#tail-->","retrieved":1636630587387},{"contents":"<!--fragment#93ddb4ffa8#head--> Woodae <!--fragment#93ddb4ffa8#tail-->","retrieved":1636630587391},{"contents":"<!--fragment#12ce4647353#head--> 하이량 <!--fragment#12ce4647353#tail-->","retrieved":1636630587391},{"contents":"<!--fragment#f7fa322734#head--> PicoVello <!--fragment#f7fa322734#tail-->","retrieved":1636630587391},{"contents":"<!--fragment#16f96f71437#head--> GRACE SHIN (그레이스 신) <!--fragment#16f96f71437#tail-->","retrieved":1636630587391},{"contents":"<!--fragment#d73387a1b6#head--> 하범석 <!--fragment#d73387a1b6#tail-->","retrieved":1636630587391},{"contents":"<!--fragment#573b336822#head--> P!nUp (핀업) <!--fragment#573b336822#tail-->","retrieved":1636630587391},{"contents":"<!--fragment#283b0198bc#head--> Billlie <!--fragment#283b0198bc#tail-->","retrieved":1636630587391},{"contents":"<!--fragment#16d7f8117f0#head--> 루 (LEW) <!--fragment#16d7f8117f0#tail-->","retrieved":1636630587391},{"contents":"<!--fragment#16ce61f932a#head--> JUNNY (주니) <!--fragment#16ce61f932a#tail-->","retrieved":1636630587391},{"contents":"<!--fragment#15971d2ab97#head--> 아이씨유 (ICU) <!--fragment#15971d2ab97#tail-->","retrieved":1636630587391},{"contents":"<!--fragment#1038b843d29#head--> SIM2 <!--fragment#1038b843d29#tail-->","retrieved":1636630587404},{"contents":"<!--fragment#1484f93c524#head--> 요조 <!--fragment#1484f93c524#tail-->","retrieved":1636630587404},{"contents":"<!--fragment#13ab3933a02#head--> 에일리(Ailee) <!--fragment#13ab3933a02#tail-->","retrieved":1636630587406},{"contents":"<!--fragment#754db0d719#head--> 설아 (우주소녀) <!--fragment#754db0d719#tail-->","retrieved":1636630587406},{"contents":"<!--fragment#2dbed59f30#head--> 옐로우 스트링 보이스 <!--fragment#2dbed59f30#tail-->","retrieved":1636630587406},{"contents":"<!--fragment#9357bd0282#head--> 조성민 <!--fragment#9357bd0282#tail-->","retrieved":1636630587406},{"contents":"<!--fragment#124251b0537#head--> 오치영 <!--fragment#124251b0537#tail-->","retrieved":1636630587406},{"contents":"<!--fragment#68192c1a2b#head--> 오씨 (oc) <!--fragment#68192c1a2b#tail-->","retrieved":1636630587406},{"contents":"<!--fragment#d77141f01d#head--> 라날로그 (Lanalogue) <!--fragment#d77141f01d#tail-->","retrieved":1636630587406},{"contents":"<!--fragment#bf5d69553d#head--> 프롬올투휴먼 (from all to human) <!--fragment#bf5d69553d#tail-->","retrieved":1636630587406},{"contents":"<!--fragment#21459d6ed7#head--> psv:gun <!--fragment#21459d6ed7#tail-->","retrieved":1636630587406},{"contents":"<!--fragment#11753f4f07d#head--> Blew.D <!--fragment#11753f4f07d#tail-->","retrieved":1636630587408},{"contents":"<!--fragment#d946d91883#head--> 더 데이지 (The Daisy) <!--fragment#d946d91883#tail-->","retrieved":1636630587435},{"contents":"<!--fragment#d99319973#head--> 천소아 <!--fragment#d99319973#tail-->","retrieved":1636630587436},{"contents":"<!--fragment#b09ba1b9e7#head--> VICTON (빅톤) <!--fragment#b09ba1b9e7#tail-->","retrieved":1636630587436},{"contents":"<!--fragment#12d7122e0d8#head--> 띵크 (th!nk) <!--fragment#12d7122e0d8#tail-->","retrieved":1636630587437},{"contents":"<!--fragment#120aabe64ca#head--> 칼레파 (KalRePa) <!--fragment#120aabe64ca#tail-->","retrieved":1636630587438},{"contents":"<!--fragment#1568d32b73#head--> Hodge <!--fragment#1568d32b73#tail-->","retrieved":1636630587438},{"contents":"<!--fragment#41c9e61423#head--> 원어스 (ONEUS) <!--fragment#41c9e61423#tail-->","retrieved":1636630587439},{"contents":"<!--fragment#14030114b58#head--> 라운드어바웃 (RoundAbout) <!--fragment#14030114b58#tail-->","retrieved":1636630587440},{"contents":"<!--fragment#16ff0d9555e#head--> noovv <!--fragment#16ff0d9555e#tail-->","retrieved":1636630587441},{"contents":"<!--fragment#f8f1576df7#head--> 레코드벨 <!--fragment#f8f1576df7#tail-->","retrieved":1636630587442},{"contents":"<!--fragment#2a0f82ef42#head--> 크록 (CROQ) <!--fragment#2a0f82ef42#tail-->","retrieved":1636630587443},{"contents":"<!--fragment#56a47ef67f#head--> 이소정 <!--fragment#56a47ef67f#tail-->","retrieved":1636630587444},{"contents":"<!--fragment#1346165b4e1#head--> Moon (혜원) <!--fragment#1346165b4e1#tail-->","retrieved":1636630587445},{"contents":"<!--fragment#ffbfb6f4f5#head--> 전인권 <!--fragment#ffbfb6f4f5#tail-->","retrieved":1636630587446},{"contents":"<!--fragment#10e428129f#head--> 엄지영 <!--fragment#10e428129f#tail-->","retrieved":1636630587447},{"contents":"<!--fragment#1408efe7cb4#head--> 보라미유 <!--fragment#1408efe7cb4#tail-->","retrieved":1636630587449},{"contents":"<!--fragment#14be6656686#head--> 이나래 <!--fragment#14be6656686#tail-->","retrieved":1636630587450},{"contents":"<!--fragment#f870a094bd#head--> ABOUT (어바웃) <!--fragment#f870a094bd#tail-->","retrieved":1636630587451},{"contents":"<!--fragment#4343738ff7#head--> 셔츠 보이 프랭크 <!--fragment#4343738ff7#tail-->","retrieved":1636630587452},{"contents":"<!--fragment#7d3ad16ebf#head--> 징고 (ZINGO) <!--fragment#7d3ad16ebf#tail-->","retrieved":1636630587454},{"contents":"<!--fragment#9f5724ed65#head--> 브로맨스 (VROMANCE) <!--fragment#9f5724ed65#tail-->","retrieved":1636630587455},{"contents":"<!--fragment#5daaa3e3e9#head--> muhpy <!--fragment#5daaa3e3e9#tail-->","retrieved":1636630587456},{"contents":"<!--fragment#7e230846d8#head--> 투탁 핀셔 <!--fragment#7e230846d8#tail-->","retrieved":1636630587457},{"contents":"<!--fragment#b5274b1e53#head--> 빨간의자 <!--fragment#b5274b1e53#tail-->","retrieved":1636630587458},{"contents":"<!--fragment#5f36442b2b#head--> 로즈아나 (Rosanna) <!--fragment#5f36442b2b#tail-->","retrieved":1636630587459},{"contents":"<!--fragment#8752d06f3d#head--> homezone <!--fragment#8752d06f3d#tail-->","retrieved":1636630587460},{"contents":"<!--fragment#f99cf25cbe#head--> livur <!--fragment#f99cf25cbe#tail-->","retrieved":1636630587461},{"contents":"<!--fragment#1717ff55b38#head--> mmddyy (맨디) <!--fragment#1717ff55b38#tail-->","retrieved":1636630587462},{"contents":"<!--fragment#14233e3be59#head--> THE PIECES(더 피스) <!--fragment#14233e3be59#tail-->","retrieved":1636630587463},{"contents":"<!--fragment#ab1f8b1085#head--> 황치열 <!--fragment#ab1f8b1085#tail-->","retrieved":1636630587465},{"contents":"<!--fragment#4e9c7a6b55#head--> 임재현 <!--fragment#4e9c7a6b55#tail-->","retrieved":1636630587468},{"contents":"<!--fragment#101abb2118b#head--> 오브어스 <!--fragment#101abb2118b#tail-->","retrieved":1636630587469},{"contents":"<!--fragment#16a139c733a#head--> 길구봉구 <!--fragment#16a139c733a#tail-->","retrieved":1636630587470},{"contents":"<!--fragment#8d2e62b79#head--> 폴립 (POLYP) <!--fragment#8d2e62b79#tail-->","retrieved":1636630587471},{"contents":"<!--fragment#633379b80#head--> 루나 (LUNA) <!--fragment#633379b80#tail-->","retrieved":1636630587472},{"contents":"<!--fragment#5ba33fb4b1#head--> 카야 (Kaya) <!--fragment#5ba33fb4b1#tail-->","retrieved":1636630587473},{"contents":"<!--fragment#f83829751f#head--> 우현하 <!--fragment#f83829751f#tail-->","retrieved":1636630587474},{"contents":"<!--fragment#ffa466938f#head--> INJAE (인재) <!--fragment#ffa466938f#tail-->","retrieved":1636630587475},{"contents":"<!--fragment#1a3f52772e#head--> BIG Naughty (서동현) <!--fragment#1a3f52772e#tail-->","retrieved":1636630587476},{"contents":"<!--fragment#169f421375c#head--> 미카엘 (M!KYLE) <!--fragment#169f421375c#tail-->","retrieved":1636630587477},{"contents":"<!--fragment#17aabaf5eab#head--> Dine On <!--fragment#17aabaf5eab#tail-->","retrieved":1636630587478},{"contents":"<!--fragment#ea24bea9fc#head--> 차정민 (NtoL) <!--fragment#ea24bea9fc#tail-->","retrieved":1636630587479},{"contents":"<!--fragment#c16307f447#head--> 민 <!--fragment#c16307f447#tail-->","retrieved":1636630587480},{"contents":"<!--fragment#17af16ea29f#head--> 텍사스가라오케 (Texas Karaoke) <!--fragment#17af16ea29f#tail-->","retrieved":1636630587481},{"contents":"<!--fragment#17865a139ba#head--> 유정식 <!--fragment#17865a139ba#tail-->","retrieved":1636630587482},{"contents":"<!--fragment#14890fec255#head--> 콘다 (Conda) <!--fragment#14890fec255#tail-->","retrieved":1636630587483},{"contents":"<!--fragment#475558089b#head--> 이새봄 <!--fragment#475558089b#tail-->","retrieved":1636630587484},{"contents":"<!--fragment#21bc639aa4#head--> Jomalxne <!--fragment#21bc639aa4#tail-->","retrieved":1636630587486},{"contents":"<!--fragment#13c5233a5fa#head--> Jessica (제시카) <!--fragment#13c5233a5fa#tail-->","retrieved":1636630587487},{"contents":"<!--fragment#11b52a02568#head--> CMBY (코마보이) <!--fragment#11b52a02568#tail-->","retrieved":1636630587488},{"contents":"<!--fragment#b3c3d1854c#head--> 플랏나인 <!--fragment#b3c3d1854c#tail-->","retrieved":1636630587489},{"contents":"<!--fragment#510318f005#head--> 필리 <!--fragment#510318f005#tail-->","retrieved":1636630587490},{"contents":"<!--fragment#9b4b011600#head--> 진 <!--fragment#9b4b011600#tail-->","retrieved":1636630587491},{"contents":"<!--fragment#756e763b8c#head--> heyden <!--fragment#756e763b8c#tail-->","retrieved":1636630587492},{"contents":"<!--fragment#170a181b31c#head--> 소연 (LABOUM) <!--fragment#170a181b31c#tail-->","retrieved":1636630587494},{"contents":"<!--fragment#34860ef7eb#head--> 임세모 <!--fragment#34860ef7eb#tail-->","retrieved":1636630587495}]}