{"title":"FLO ─ New Track","url":"https://www.music-flo.com/new/track?sortType=KPOP","favicon":"https://www.music-flo.com/favicon.ico","elements":[{"title":"FAKE RAPPERS KILLER (Feat. northfacegawd)","contents":"<!--fragment#144798f5953#head-->수퍼비<!--fragment#144798f5953#tail-->","link":"https://www.music-flo.com/detail/album/edzzadiny/albumtrack","retrieved":1632994765656,"image":"https://cdn.music-flo.com/image/v2/album/329/610/06/04/406610329_6153f547_s.jpg?1632892234237/dims/resize/140x140/quality/90"},{"title":"직진","contents":"<!--fragment#849bf40003#head-->딘딘 (DINDIN)<!--fragment#849bf40003#tail-->","link":"https://www.music-flo.com/detail/album/edzzaneii/albumtrack","retrieved":1632994765657,"image":"https://cdn.music-flo.com/image/v2/album/433/612/06/04/406612433_615418d4_s.jpg?1632901333391/dims/resize/140x140/quality/90"},{"title":"Remember","contents":"<!--fragment#559a0c1898#head-->유라 (youra)<!--fragment#559a0c1898#tail-->","link":"https://www.music-flo.com/detail/album/edzlylnhn/albumtrack","retrieved":1632994765667,"image":"https://cdn.music-flo.com/image/v2/album/282/595/06/04/406595282_61529eaa_o.jpg?1632804524062/dims/resize/140x140/quality/90"},{"title":"내 사람입니다 (2021)","contents":"<!--fragment#5702a44a69#head-->김경록<!--fragment#5702a44a69#tail-->","link":"https://www.music-flo.com/detail/album/edzzdyain/albumtrack","retrieved":1632994765668,"image":"https://cdn.music-flo.com/image/v2/album/132/609/06/04/406609132_6153dd00_s.jpg?1632886019681/dims/resize/140x140/quality/90"},{"title":"DISTORTION","contents":"<!--fragment#15dee799154#head-->조하 (JOHA)<!--fragment#15dee799154#tail-->","link":"https://www.music-flo.com/detail/album/edzzadooi/albumtrack","retrieved":1632994765669,"image":"https://cdn.music-flo.com/image/v2/album/773/610/06/04/406610773_6153fcae_s.jpg?1632894127000/dims/resize/x140/quality/90"},{"title":"Hot & Cold (2021)","contents":"<!--fragment#8d9cebec46#head-->ARIAZ (아리아즈)<!--fragment#8d9cebec46#tail-->","link":"https://www.music-flo.com/detail/album/edzzdhyno/albumtrack","retrieved":1632994765670,"image":"https://cdn.music-flo.com/image/v2/album/927/608/06/04/406608927_6153d6bf_s.jpg?1632884418142/dims/resize/140x140/quality/90"},{"title":"놀이터","contents":"<!--fragment#3ac478ca90#head-->한기란<!--fragment#3ac478ca90#tail-->","link":"https://www.music-flo.com/detail/album/edzlyyzol/albumtrack","retrieved":1632994765672,"image":"https://cdn.music-flo.com/image/v2/album/675/599/06/04/406599675_61544821_o.jpg?1632913443016/dims/resize/140x140/quality/90"},{"title":"아무도 될 수 없다는 게","contents":"<!--fragment#1548f6fb34e#head-->원써겐 (1sagain)<!--fragment#1548f6fb34e#tail-->","link":"https://www.music-flo.com/detail/album/edzzandnz/albumtrack","retrieved":1632994765561},{"title":"혹시나 하는 말","contents":"<!--fragment#57772ed989#head-->결 (KYUL)<!--fragment#57772ed989#tail-->","link":"https://www.music-flo.com/detail/album/edzlhdoil/albumtrack","retrieved":1632973233130},{"title":"밤이 좋아서 (Feat. 용훈 of 원위(ONEWE))","contents":"<!--fragment#39950b0672#head-->런치박스 (lunCHbox)<!--fragment#39950b0672#tail-->","link":"https://www.music-flo.com/detail/album/edzlyyyie/albumtrack","retrieved":1632994765573},{"title":"Us, in Memories","contents":"<!--fragment#787822bd30#head-->Janet Suhh (자넷서)<!--fragment#787822bd30#tail-->","link":"https://www.music-flo.com/detail/album/edzzdyale/albumtrack","retrieved":1632973233133},{"title":"폭주 feat. BUSYNESSBOY (prod.King South G)","contents":"<!--fragment#ee6c676b41#head-->KING SOUTH G<!--fragment#ee6c676b41#tail-->","link":"https://www.music-flo.com/detail/album/edzzanlhz/albumtrack","retrieved":1632994765590},{"title":"주말 (Vocal 지묵)","contents":"<!--fragment#176f9d1847#head-->그네<!--fragment#176f9d1847#tail-->","link":"https://www.music-flo.com/detail/album/edzlylyio/albumtrack","retrieved":1632994765591},{"title":"BANDS TO THA ROOF","contents":"<!--fragment#7c8cc382e6#head-->Mac9 (맥나인)<!--fragment#7c8cc382e6#tail-->","link":"https://www.music-flo.com/detail/album/edzlyhloe/albumtrack","retrieved":1632994765592},{"title":"이제 헤어지는 건가 봐","contents":"<!--fragment#4a87d86e64#head-->오현우<!--fragment#4a87d86e64#tail-->","link":"https://www.music-flo.com/detail/album/edzlylzaz/albumtrack","retrieved":1632973233132},{"title":"꿈처럼 포근한 거야 (Feat. 모닝커피 (Morning Coffee))","contents":"<!--fragment#1629363e6ae#head-->브런치 레시피 (Brunch recipe)<!--fragment#1629363e6ae#tail-->","link":"https://www.music-flo.com/detail/album/edzzadnzd/albumtrack","retrieved":1632973233057},{"title":"너와 나 (Feat. 소울 크라이)","contents":"<!--fragment#6fe65ae1fa#head-->마멀레이드 키친 (Marmalade Kitchen)<!--fragment#6fe65ae1fa#tail-->","link":"https://www.music-flo.com/detail/album/edzzadenl/albumtrack","retrieved":1632973233049},{"title":"morse moss(skit)","contents":"<!--fragment#1b2b42db75#head-->한국사람<!--fragment#1b2b42db75#tail-->","link":"https://www.music-flo.com/detail/album/edzzdnhzo/albumtrack","retrieved":1632973233130},{"title":"사랑은 언제나 목마르다 (N번째 연애 X 이해리 (다비치))","contents":"<!--fragment#27ee164980#head-->이해리<!--fragment#27ee164980#tail-->","link":"https://www.music-flo.com/detail/album/edzlyondz/albumtrack","retrieved":1632908362538},{"title":"헤어진 날의 일기","contents":"<!--fragment#1d44739524#head-->뱅크<!--fragment#1d44739524#tail-->","link":"https://www.music-flo.com/detail/album/edzlyydnh/albumtrack","retrieved":1632973233048},{"title":"You Lie So Good","contents":"<!--fragment#320562df25#head-->오드리노 (Audrey No)<!--fragment#320562df25#tail-->","link":"https://www.music-flo.com/detail/album/edzzanide/albumtrack","retrieved":1632973233047},{"title":"버디찬스","contents":"<!--fragment#12cce1fd71b#head-->신나라<!--fragment#12cce1fd71b#tail-->","link":"https://www.music-flo.com/detail/album/edzzadeii/albumtrack","retrieved":1632973233138},{"title":"너와 밤과 별","contents":"<!--fragment#419d1adbd4#head-->김새벽<!--fragment#419d1adbd4#tail-->","link":"https://www.music-flo.com/detail/album/edzzdhlhh/albumtrack","retrieved":1632973233052},{"title":"처음 만난 그때처럼","contents":"<!--fragment#fa7e7fa1df#head-->김필<!--fragment#fa7e7fa1df#tail-->","link":"https://www.music-flo.com/detail/album/edzlyodaa/albumtrack","retrieved":1632908362537},{"title":"I′ll never stop dreaming","contents":"<!--fragment#248fb3755#head-->김준휘<!--fragment#248fb3755#tail-->","link":"https://www.music-flo.com/detail/album/edzzdhooe/albumtrack","retrieved":1632973233137},{"title":"Lover Like Me","contents":"<!--fragment#ceb718edb6#head-->CL<!--fragment#ceb718edb6#tail-->","link":"https://www.music-flo.com/detail/album/edzllaiho/albumtrack","retrieved":1632890962073},{"title":"버리러 가는 길","contents":"<!--fragment#11ef2369908#head-->최윤정<!--fragment#11ef2369908#tail-->","link":"https://www.music-flo.com/detail/album/edzzaneha/albumtrack","retrieved":1632973233053},{"title":"ICONS","contents":"<!--fragment#ecc7056eb8#head-->핫이슈 (HOT ISSUE)<!--fragment#ecc7056eb8#tail-->","link":"https://www.music-flo.com/detail/album/edzlyonly/albumtrack","retrieved":1632908362548},{"title":"Circle","contents":"<!--fragment#8cb409fe4b#head-->WEEKDAY<!--fragment#8cb409fe4b#tail-->","link":"https://www.music-flo.com/detail/album/edzzdyaoo/albumtrack","retrieved":1632973233054},{"title":"Perfume","contents":"<!--fragment#13448fa2d22#head-->멜로우 키친<!--fragment#13448fa2d22#tail-->","link":"https://www.music-flo.com/detail/album/edzlyoaee/albumtrack","retrieved":1632973233050},{"title":"행복으로 키운 오렌지","contents":"<!--fragment#12c47735182#head-->신온유<!--fragment#12c47735182#tail-->","link":"https://www.music-flo.com/detail/album/edzlyiyod/albumtrack","retrieved":1632908362469},{"title":"20세기 사람들 (Vocal by Zion.T)","contents":"<!--fragment#176793c0149#head-->강승원<!--fragment#176793c0149#tail-->","link":"https://www.music-flo.com/detail/album/edzlyoaei/albumtrack","retrieved":1632908362547},{"title":"Sincere Love (Explicit Ver.)","contents":"<!--fragment#2d7aa411e6#head-->entoy<!--fragment#2d7aa411e6#tail-->","link":"https://www.music-flo.com/detail/album/edziznoaa/albumtrack","retrieved":1632908362468},{"title":"BEAM","contents":"<!--fragment#153d05bd5e9#head-->TOMMY YANG<!--fragment#153d05bd5e9#tail-->","link":"https://www.music-flo.com/detail/album/edzlhaiez/albumtrack","retrieved":1632908362547},{"title":"엄마","contents":"<!--fragment#13cee0da33c#head-->보이킴 (Boy Kim)<!--fragment#13cee0da33c#tail-->","link":"https://www.music-flo.com/detail/album/edzzdyell/albumtrack","retrieved":1632973233067},{"title":"악연 (Dark Dream)","contents":"<!--fragment#12eb5052972#head-->엘라스트 (E'LAST)<!--fragment#12eb5052972#tail-->","link":"https://www.music-flo.com/detail/album/edzlonihd/albumtrack","retrieved":1632908362549},{"title":"먼지","contents":"<!--fragment#f42cee354c#head-->화자<!--fragment#f42cee354c#tail-->","link":"https://www.music-flo.com/detail/album/edzlhayli/albumtrack","retrieved":1632886856991},{"title":"스르르(zZZ)(feat.홍의진)","contents":"<!--fragment#4cb992af55#head-->Soup<!--fragment#4cb992af55#tail-->","link":"https://www.music-flo.com/detail/album/edzlyeohe/albumtrack","retrieved":1632908362483},{"title":"STAR","contents":"<!--fragment#15c2e47e360#head-->KINIE.K (키니케이)<!--fragment#15c2e47e360#tail-->","link":"https://www.music-flo.com/detail/album/edzlyeyzl/albumtrack","retrieved":1632908362470},{"title":"봄날","contents":"<!--fragment#919ec9b5f3#head-->naru (나루)<!--fragment#919ec9b5f3#tail-->","link":"https://www.music-flo.com/detail/album/edzlhnhly/albumtrack","retrieved":1632886856991},{"title":"인디언","contents":"<!--fragment#7b3bcc4ff9#head-->Re.JACK(리잭)<!--fragment#7b3bcc4ff9#tail-->","link":"https://www.music-flo.com/detail/album/edzlhnlle/albumtrack","retrieved":1632908362495},{"title":"Alone (Feat. Austn)","contents":"<!--fragment#632fe7f497#head-->숨셔<!--fragment#632fe7f497#tail-->","link":"https://www.music-flo.com/detail/album/edzlyolhz/albumtrack","retrieved":1632886856993},{"title":"별이다","contents":"<!--fragment#e0a0366f18#head-->버블 시스터즈<!--fragment#e0a0366f18#tail-->","link":"https://www.music-flo.com/detail/album/edzlhieza/albumtrack","retrieved":1632886856992},{"title":"뱃노래","contents":"<!--fragment#15a4988a5f0#head-->sEODo BAND (서도밴드)<!--fragment#15a4988a5f0#tail-->","link":"https://www.music-flo.com/detail/album/edzlyzaze/albumtrack","retrieved":1632886856933},{"title":"Drama","contents":"<!--fragment#cee42d0374#head-->나웅재 (NAUNGJAE)<!--fragment#cee42d0374#tail-->","link":"https://www.music-flo.com/detail/album/edzlyylee/albumtrack","retrieved":1632908362499},{"title":"10 Minutes","contents":"<!--fragment#5abf21a8e#head-->원슈타인<!--fragment#5abf21a8e#tail-->","link":"https://www.music-flo.com/detail/album/edzlyleny/albumtrack","retrieved":1632821960658},{"title":"Easty (feat. SIKBOY)","contents":"<!--fragment#152d894644c#head-->Yonge Jaundice (영 잔디스)<!--fragment#152d894644c#tail-->","link":"https://www.music-flo.com/detail/album/edzlyeone/albumtrack","retrieved":1632886856994},{"title":"Little Things (Feat. YELO)","contents":"<!--fragment#4edb08c2d3#head-->TJ Monterde<!--fragment#4edb08c2d3#tail-->","link":"https://www.music-flo.com/detail/album/edzloadyz/albumtrack","retrieved":1632908362502},{"title":"니가 좋아했으면 해","contents":"<!--fragment#71f1060bf3#head-->우디 (Woody)<!--fragment#71f1060bf3#tail-->","link":"https://www.music-flo.com/detail/album/edzlhdzdd/albumtrack","retrieved":1632821960664},{"title":"Hate Me","contents":"<!--fragment#167127ef087#head-->오아 (OA)<!--fragment#167127ef087#tail-->","link":"https://www.music-flo.com/detail/album/edzlyholh/albumtrack","retrieved":1632886856930},{"title":"TWILIGHT (Ooh)","contents":"<!--fragment#c28342c76b#head-->미카엘 (M!KYLE)<!--fragment#c28342c76b#tail-->","link":"https://www.music-flo.com/detail/album/edzllhydi/albumtrack","retrieved":1632886856995},{"title":"보내 (BONE)","contents":"<!--fragment#14e0cbfd158#head-->배준렬 (BJR)<!--fragment#14e0cbfd158#tail-->","link":"https://www.music-flo.com/detail/album/edzlyloyd/albumtrack","retrieved":1632886856937},{"title":"Blessed (Feat. GSoul)","contents":"<!--fragment#16202f3d3e#head-->THAMA<!--fragment#16202f3d3e#tail-->","link":"https://www.music-flo.com/detail/album/edzlhdzii/albumtrack","retrieved":1632821960660},{"title":"사랑하고 싶다","contents":"<!--fragment#8c5c4158a3#head-->유승우<!--fragment#8c5c4158a3#tail-->","link":"https://www.music-flo.com/detail/album/edzlhiayh/albumtrack","retrieved":1632821960659},{"title":"나에게로 Come To Me","contents":"<!--fragment#139979c1d98#head-->니쥬 (nijuu)<!--fragment#139979c1d98#tail-->","link":"https://www.music-flo.com/detail/album/edzlonini/albumtrack","retrieved":1632886856947},{"title":"사랑은 갑자기 내 맘에 들어와","contents":"<!--fragment#1552f8249e5#head-->천소아<!--fragment#1552f8249e5#tail-->","link":"https://www.music-flo.com/detail/album/edzlyezdl/albumtrack","retrieved":1632886856945},{"title":"Queen","contents":"<!--fragment#124fda464b3#head-->Paxy (팍시)<!--fragment#124fda464b3#tail-->","link":"https://www.music-flo.com/detail/album/edzlynyna/albumtrack","retrieved":1632886856942},{"title":"머리 없어도","contents":"<!--fragment#164fbf5d736#head-->스칼렛킴<!--fragment#164fbf5d736#tail-->","link":"https://www.music-flo.com/detail/album/edzlhnany/albumtrack","retrieved":1632886856940},{"title":"이별 없는 날","contents":"<!--fragment#95eb659c12#head-->정유진<!--fragment#95eb659c12#tail-->","link":"https://www.music-flo.com/detail/album/edzlhdydn/albumtrack","retrieved":1632821960665},{"title":"콩깍지","contents":"<!--fragment#172f2aa751c#head-->싸이퍼 (Ciipher)<!--fragment#172f2aa751c#tail-->","link":"https://www.music-flo.com/detail/album/edzlhianl/albumtrack","retrieved":1632821960661},{"title":"너를 부를때…(Prod. PATEKO(파테코),Kid Wine)","contents":"<!--fragment#d9a1067e46#head-->WetBoy<!--fragment#d9a1067e46#tail-->","link":"https://www.music-flo.com/detail/album/edzloahln/albumtrack","retrieved":1632821960563},{"title":"7000RPM","contents":"<!--fragment#6aa1a96739#head-->KARDI (카디)<!--fragment#6aa1a96739#tail-->","link":"https://www.music-flo.com/detail/album/edzlhneey/albumtrack","retrieved":1632800429329},{"title":"조용히 눈을 감고 (Band ver.)","contents":"<!--fragment#7ee556f2c0#head-->모던다락방<!--fragment#7ee556f2c0#tail-->","link":"https://www.music-flo.com/detail/album/edzlhdzla/albumtrack","retrieved":1632886856946},{"title":"RESONATE","contents":"<!--fragment#c97ea3e672#head-->WANNA (워나)<!--fragment#c97ea3e672#tail-->","link":"https://www.music-flo.com/detail/album/edzlhdyye/albumtrack","retrieved":1632886856939},{"title":"그냥 웃자","contents":"<!--fragment#10ea4d7fb39#head-->김다현<!--fragment#10ea4d7fb39#tail-->","link":"https://www.music-flo.com/detail/album/edzlhnlzi/albumtrack","retrieved":1632800429336},{"title":"Move! (With. 루루, 라라)","contents":"<!--fragment#14ddc7c001d#head-->박문치<!--fragment#14ddc7c001d#tail-->","link":"https://www.music-flo.com/detail/album/edzlhanhe/albumtrack","retrieved":1632800429335},{"title":"Closer (Feat. ARON)","contents":"<!--fragment#11087165b8a#head-->Choisul<!--fragment#11087165b8a#tail-->","link":"https://www.music-flo.com/detail/album/edzlhddhz/albumtrack","retrieved":1632821960602},{"title":"Oh My Daddy","contents":"<!--fragment#69dbdb2554#head-->제이블랙 &amp; 제이핑크 (J BLACK &amp; J PINK)<!--fragment#69dbdb2554#tail-->","link":"https://www.music-flo.com/detail/album/edzloeyoh/albumtrack","retrieved":1632821960561},{"title":"BAD LOVE","contents":"<!--fragment#10937f296ba#head-->키 (KEY)<!--fragment#10937f296ba#tail-->","link":"https://www.music-flo.com/detail/album/edzlhadey/albumtrack","retrieved":1632735564056},{"title":"겨울바다","contents":"<!--fragment#9f979c502#head-->최재현<!--fragment#9f979c502#tail-->","link":"https://www.music-flo.com/detail/album/edzloeoio/albumtrack","retrieved":1632821960585},{"title":"Now carti on my wrist whats next","contents":"<!--fragment#1754573d790#head-->zzuno だいすき!<!--fragment#1754573d790#tail-->","link":"https://www.music-flo.com/detail/album/edzlhidaz/albumtrack","retrieved":1632821960564},{"title":"Align","contents":"<!--fragment#62fa2a145d#head-->Viral Affair<!--fragment#62fa2a145d#tail-->","link":"https://www.music-flo.com/detail/album/edzlhalih/albumtrack","retrieved":1632800429274},{"title":"문득 (Duet with 송희진)","contents":"<!--fragment#cffd241fc0#head-->도운 (DAY6)<!--fragment#cffd241fc0#tail-->","link":"https://www.music-flo.com/detail/album/edzlhdyzh/albumtrack","retrieved":1632735564058},{"title":"21g","contents":"<!--fragment#10d100b6eb6#head-->Meek Drib<!--fragment#10d100b6eb6#tail-->","link":"https://www.music-flo.com/detail/album/edzlhadzd/albumtrack","retrieved":1632821960585},{"title":"우린 마를 리 없었지","contents":"<!--fragment#aa204a6f6#head-->겸 (GYE0M)<!--fragment#aa204a6f6#tail-->","link":"https://www.music-flo.com/detail/album/edzlollly/albumtrack","retrieved":1632800429274},{"title":"Tree","contents":"<!--fragment#17806c7b2c5#head-->오월오일 ( 五月五日 )<!--fragment#17806c7b2c5#tail-->","link":"https://www.music-flo.com/detail/album/edzloleoe/albumtrack","retrieved":1632800429274},{"title":"Misfit (Prod. GRIO)","contents":"<!--fragment#15124381bb9#head-->CLIQUE<!--fragment#15124381bb9#tail-->","link":"https://www.music-flo.com/detail/album/edzloeeyy/albumtrack","retrieved":1632800429274},{"title":"CHERRY","contents":"<!--fragment#130dc4e43b8#head-->AB6IX (에이비식스)<!--fragment#130dc4e43b8#tail-->","link":"https://www.music-flo.com/detail/album/edzlhazol/albumtrack","retrieved":1632735564057},{"title":"She got somethin'","contents":"<!--fragment#145e15b4bb#head-->몰리디<!--fragment#145e15b4bb#tail-->","link":"https://www.music-flo.com/detail/album/edzlhdzia/albumtrack","retrieved":1632800429274},{"title":"Just Reply","contents":"<!--fragment#7e632bcaca#head-->뷰티핸섬<!--fragment#7e632bcaca#tail-->","link":"https://www.music-flo.com/detail/album/edzlhdzno/albumtrack","retrieved":1632800429337},{"title":"잘 자 (Feat. VEL)","contents":"<!--fragment#158e914d776#head-->if.iwere (입하월)<!--fragment#158e914d776#tail-->","link":"https://www.music-flo.com/detail/album/edzlhdzyo/albumtrack","retrieved":1632800429275},{"title":"너의 눈물이 나의 눈을 적실 때","contents":"<!--fragment#11fa3a74de5#head-->에일리(Ailee)<!--fragment#11fa3a74de5#tail-->","link":"https://www.music-flo.com/detail/album/edzlhdlld/albumtrack","retrieved":1632735564059},{"title":"강강술래 (경주 & 안동) (Feat. sogumm) (Prod. GRAY)","contents":"<!--fragment#5d7a3fbb69#head-->우원재<!--fragment#5d7a3fbb69#tail-->","link":"https://www.music-flo.com/detail/album/edzlolede/albumtrack","retrieved":1632735564062},{"title":"쿵쿵쿵","contents":"<!--fragment#13e577f6d92#head-->Liquor (리쿼)<!--fragment#13e577f6d92#tail-->","link":"https://www.music-flo.com/detail/album/edzlhneei/albumtrack","retrieved":1632800429344},{"title":"Same Things Anymore","contents":"<!--fragment#17057891b14#head-->Uzuhan (우주한)<!--fragment#17057891b14#tail-->","link":"https://www.music-flo.com/detail/album/edzlhdzad/albumtrack","retrieved":1632800429274},{"title":"아름다운 걸","contents":"<!--fragment#3771e49c67#head-->백퍼센트<!--fragment#3771e49c67#tail-->","link":"https://www.music-flo.com/detail/album/edzlhdydo/albumtrack","retrieved":1632735564062},{"title":"웃음소리 (Vocal by 임단우)","contents":"<!--fragment#22d4601d6e#head-->이진우<!--fragment#22d4601d6e#tail-->","link":"https://www.music-flo.com/detail/album/edzllnzai/albumtrack","retrieved":1632800429274},{"title":"Promise","contents":"<!--fragment#bfc0d4723#head-->태헌<!--fragment#bfc0d4723#tail-->","link":"https://www.music-flo.com/detail/album/edzlhnnzz/albumtrack","retrieved":1632800429274},{"title":"아인슈타인 (feat. Louie) (Prod. Badtree)","contents":"<!--fragment#db61551a7d#head-->스카프 (SC4F)<!--fragment#db61551a7d#tail-->","link":"https://www.music-flo.com/detail/album/edzloeeoz/albumtrack","retrieved":1632735563973},{"title":"기다릴게","contents":"<!--fragment#9d9187c710#head-->후아유<!--fragment#9d9187c710#tail-->","link":"https://www.music-flo.com/detail/album/edzloliiz/albumtrack","retrieved":1632735563917},{"title":"Sticker","contents":"<!--fragment#9eaa98b50f#head-->Seiren 8<!--fragment#9eaa98b50f#tail-->","link":"https://www.music-flo.com/detail/album/edzlhadno/albumtrack","retrieved":1632800429278},{"title":"Flower (Feat. 김하은, centipede)","contents":"<!--fragment#b932670258#head-->공든 (ODEUN)<!--fragment#b932670258#tail-->","link":"https://www.music-flo.com/detail/album/edzlhdzha/albumtrack","retrieved":1632800429279},{"title":"초대하지 않은 손님","contents":"<!--fragment#1248f74a36d#head-->안희수(Heesu Ahn)<!--fragment#1248f74a36d#tail-->","link":"https://www.music-flo.com/detail/album/edzlooido/albumtrack","retrieved":1632735564063},{"title":"Echo (Feat. Omega Sapien)","contents":"<!--fragment#f6b0bbe692#head-->이수호<!--fragment#f6b0bbe692#tail-->","link":"https://www.music-flo.com/detail/album/edzllhyde/albumtrack","retrieved":1632735563920},{"title":"Santa Monica","contents":"<!--fragment#8f53d5e573#head-->NIK<!--fragment#8f53d5e573#tail-->","link":"https://www.music-flo.com/detail/album/edzlooidz/albumtrack","retrieved":1632735563920},{"title":"사랑하지 않았을 거야","contents":"<!--fragment#e2dc8b3a48#head-->장희원<!--fragment#e2dc8b3a48#tail-->","link":"https://www.music-flo.com/detail/album/edzlollzn/albumtrack","retrieved":1632718201493},{"title":"Fly Away (feat. Eily)","contents":"<!--fragment#7839f80e0e#head-->lofi<!--fragment#7839f80e0e#tail-->","link":"https://www.music-flo.com/detail/album/edzllhyei/albumtrack","retrieved":1632718201518},{"title":"tonight","contents":"<!--fragment#6ad9f80034#head-->Jimmy Brown<!--fragment#6ad9f80034#tail-->","link":"https://www.music-flo.com/detail/album/edzllhzdh/albumtrack","retrieved":1632718201497},{"title":"in the air","contents":"<!--fragment#1432158bd5a#head-->Won Jang<!--fragment#1432158bd5a#tail-->","link":"https://www.music-flo.com/detail/album/edzloeioy/albumtrack","retrieved":1632735563936},{"title":"저 인형 (Feat. 안병웅)","contents":"<!--fragment#142f9aa70a1#head-->b!ni<!--fragment#142f9aa70a1#tail-->","link":"https://www.music-flo.com/detail/album/edzlolnhy/albumtrack","retrieved":1632718201492}]}