{"title":"FLO ─ New Track","url":"https://www.music-flo.com/new/track?sortType=KPOP","favicon":"https://www.music-flo.com/favicon.ico","elements":[{"title":"XOXO","contents":"<!--fragment#144620a5f93#head-->전소미<!--fragment#144620a5f93#tail-->","link":"https://www.music-flo.com/detail/album/edzhhzdld/albumtrack","retrieved":1635500399445,"image":"https://cdn.music-flo.com/image/v2/album/050/886/06/04/406886050_617b5b80_s.jpg?1635474307485/dims/resize/140x140/quality/90"},{"title":"제자리","contents":"<!--fragment#716ad061ae#head-->존 박<!--fragment#716ad061ae#tail-->","link":"https://www.music-flo.com/detail/album/edzhhnhni/albumtrack","retrieved":1635500399480,"image":"https://cdn.music-flo.com/image/v2/album/823/882/06/04/406882823_617a8349_s.jpg?1635418955216/dims/resize/140x140/quality/90"},{"title":"인생 한잔","contents":"<!--fragment#590ab463ff#head-->정은지<!--fragment#590ab463ff#tail-->","link":"https://www.music-flo.com/detail/album/edzhohazn/albumtrack","retrieved":1635500399480,"image":"https://cdn.music-flo.com/image/v2/album/162/878/06/04/406878162_617a32a7_o.jpg?1635398313100/dims/resize/140x140/quality/90"},{"title":"낮 밤 (feat. 박재범)","contents":"<!--fragment#3af27345bd#head-->이영지<!--fragment#3af27345bd#tail-->","link":"https://www.music-flo.com/detail/album/edzhhnyil/albumtrack","retrieved":1635500399481,"image":"https://cdn.music-flo.com/image/v2/album/935/882/06/04/406882935_617a9064_s.jpg?1635422310346/dims/resize/140x140/quality/90"},{"title":"New Vision","contents":"<!--fragment#bd11885b8f#head-->Colde (콜드)<!--fragment#bd11885b8f#tail-->","link":"https://www.music-flo.com/detail/album/edzhoozan/albumtrack","retrieved":1635500399481,"image":"https://cdn.music-flo.com/image/v2/album/612/877/06/04/406877612_617a26f7_s.jpg?1635395321635/dims/resize/140x140/quality/90"},{"title":"깊어지네 (Duet With 웬디)","contents":"<!--fragment#bbb7bf73d6#head-->손태진<!--fragment#bbb7bf73d6#tail-->","link":"https://www.music-flo.com/detail/album/edzhhnyzy/albumtrack","retrieved":1635500399482,"image":"https://cdn.music-flo.com/image/v2/album/969/882/06/04/406882969_617a9478_s.jpg?1635423355166/dims/resize/140x140/quality/90"},{"title":"Tell Me","contents":"<!--fragment#e63d002cce#head-->태호 (TAE HO)<!--fragment#e63d002cce#tail-->","link":"https://www.music-flo.com/detail/album/edzhlylez/albumtrack","retrieved":1635500399483,"image":"https://cdn.music-flo.com/image/v2/album/546/859/06/04/406859546_6177d18f_o.jpg?1635242385164/dims/resize/140x140/quality/90"},{"title":"빗물에 너를 떠나보내고","contents":"<!--fragment#f3639bb76e#head-->처리 (Churry)<!--fragment#f3639bb76e#tail-->","link":"https://www.music-flo.com/detail/album/edzhledoh/albumtrack","retrieved":1635500399369},{"title":"한밤의 뮤직","contents":"<!--fragment#171f1955cb6#head-->잔나비<!--fragment#171f1955cb6#tail-->","link":"https://www.music-flo.com/detail/album/edzhzezzy/albumtrack","retrieved":1635478882916},{"title":"힘든일이","contents":"<!--fragment#1097053b8ea#head-->태비 (Taeb2)<!--fragment#1097053b8ea#tail-->","link":"https://www.music-flo.com/detail/album/edzhoadil/albumtrack","retrieved":1635500399372},{"title":"숨바꼭질 (Hide and Seek)","contents":"<!--fragment#c03c16fa6f#head-->강승원<!--fragment#c03c16fa6f#tail-->","link":"https://www.music-flo.com/detail/album/edzhoylel/albumtrack","retrieved":1635500399373},{"title":"Just Go","contents":"<!--fragment#312252a7f#head-->Nikel(617)<!--fragment#312252a7f#tail-->","link":"https://www.music-flo.com/detail/album/edzhohhho/albumtrack","retrieved":1635478882915},{"title":"반지자국","contents":"<!--fragment#ec37841a94#head-->로라<!--fragment#ec37841a94#tail-->","link":"https://www.music-flo.com/detail/album/edzhollyo/albumtrack","retrieved":1635500399376},{"title":"밤공기 (With. g1nger)","contents":"<!--fragment#99a28889d9#head-->Jflow<!--fragment#99a28889d9#tail-->","link":"https://www.music-flo.com/detail/album/edzheliid/albumtrack","retrieved":1635500399377},{"title":"No Turning Back","contents":"<!--fragment#60ce597f88#head-->펀치넬로 (punchnello)<!--fragment#60ce597f88#tail-->","link":"https://www.music-flo.com/detail/album/edzhlyyia/albumtrack","retrieved":1635478882917},{"title":"알고 싶어요","contents":"<!--fragment#117018f8ffd#head-->무명부(권민제 &amp; 박장현 &amp; 박창근)<!--fragment#117018f8ffd#tail-->","link":"https://www.music-flo.com/detail/album/edzhhadlh/albumtrack","retrieved":1635478882926},{"title":"Nag Champa","contents":"<!--fragment#14f079a5c5b#head-->마진초이 (marginchoi)<!--fragment#14f079a5c5b#tail-->","link":"https://www.music-flo.com/detail/album/edzhizand/albumtrack","retrieved":1635500399385},{"title":"매니큐어 (ManiCure)","contents":"<!--fragment#10bff1edbb9#head-->리하 (LIHA)<!--fragment#10bff1edbb9#tail-->","link":"https://www.music-flo.com/detail/album/edzhzldid/albumtrack","retrieved":1635500399385},{"title":"Total Eclipse(Duo. Denis Sungho)","contents":"<!--fragment#c7fa02cd2d#head-->박선주<!--fragment#c7fa02cd2d#tail-->","link":"https://www.music-flo.com/detail/album/edzhoyhha/albumtrack","retrieved":1635478882924},{"title":"Serious","contents":"<!--fragment#1086cc4fa26#head-->박지훈<!--fragment#1086cc4fa26#tail-->","link":"https://www.music-flo.com/detail/album/edzhoazod/albumtrack","retrieved":1635414018799},{"title":"나 그댈위해 시 한편을 쓰겠어","contents":"<!--fragment#3db13cae2d#head-->케이시 (Kassy)<!--fragment#3db13cae2d#tail-->","link":"https://www.music-flo.com/detail/album/edzhoaael/albumtrack","retrieved":1635414018814},{"title":"나에게","contents":"<!--fragment#b542a5528c#head-->미니마니 (MINIMANI)<!--fragment#b542a5528c#tail-->","link":"https://www.music-flo.com/detail/album/edzhozyzl/albumtrack","retrieved":1635478882835},{"title":"나 혼자","contents":"<!--fragment#b16968fb16#head-->란 (RAN)<!--fragment#b16968fb16#tail-->","link":"https://www.music-flo.com/detail/album/edzhooldn/albumtrack","retrieved":1635478882829},{"title":"Sunset","contents":"<!--fragment#854546dfd3#head-->SWAY (스웨이)<!--fragment#854546dfd3#tail-->","link":"https://www.music-flo.com/detail/album/edzhohniz/albumtrack","retrieved":1635478882925},{"title":"아일랜드에서 아일랜드로 prod by. Uncommon","contents":"<!--fragment#292e78fe2b#head-->김모노 (Kim MONO)<!--fragment#292e78fe2b#tail-->","link":"https://www.music-flo.com/detail/album/edzhozheh/albumtrack","retrieved":1635478882927},{"title":"Girl in New York","contents":"<!--fragment#6b2b120c32#head-->블루 (BLOO)<!--fragment#6b2b120c32#tail-->","link":"https://www.music-flo.com/detail/album/edzhohioh/albumtrack","retrieved":1635414018815},{"title":"잘 먹고 잘 사는 법","contents":"<!--fragment#89f329736#head-->더블V (송은이,김숙)<!--fragment#89f329736#tail-->","link":"https://www.music-flo.com/detail/album/edzhledad/albumtrack","retrieved":1635414018762},{"title":"One Fine Day (feat. 유자)","contents":"<!--fragment#b39d7cc0a8#head-->강필성 (PHILL)<!--fragment#b39d7cc0a8#tail-->","link":"https://www.music-flo.com/detail/album/edzhodaoo/albumtrack","retrieved":1635478882829},{"title":"LALALA","contents":"<!--fragment#ddf30016c#head-->에이로우 (ALow)<!--fragment#ddf30016c#tail-->","link":"https://www.music-flo.com/detail/album/edzhzehla/albumtrack","retrieved":1635478882829},{"title":"남쪽 (Southside) (feat. 래원(Layone))","contents":"<!--fragment#668728ead0#head-->서출구<!--fragment#668728ead0#tail-->","link":"https://www.music-flo.com/detail/album/edzhoadda/albumtrack","retrieved":1635414018845},{"title":"왜 만나 (Rollercoaster)","contents":"<!--fragment#23728a9966#head-->다크비 (DKB)<!--fragment#23728a9966#tail-->","link":"https://www.music-flo.com/detail/album/edzhlhoan/albumtrack","retrieved":1635414018765},{"title":"Cloud 9 [IDOL (아이돌 : The Coup)]","contents":"<!--fragment#43a70c324#head-->마스 (MARS)<!--fragment#43a70c324#tail-->","link":"https://www.music-flo.com/detail/album/edzhozhzz/albumtrack","retrieved":1635414018816},{"title":"Infinite City (Groundbreak Ver.)","contents":"<!--fragment#77f245254b#head-->TO1 (티오원)<!--fragment#77f245254b#tail-->","link":"https://www.music-flo.com/detail/album/edzhllyol/albumtrack","retrieved":1635414018844},{"title":"헤롱헤롱 (Feat. 한요한)","contents":"<!--fragment#345eb7ec74#head-->추서준<!--fragment#345eb7ec74#tail-->","link":"https://www.music-flo.com/detail/album/edzhoania/albumtrack","retrieved":1635414018768},{"title":"My Second Funeral","contents":"<!--fragment#e76dcae7ef#head-->메스그램 (Messgram)<!--fragment#e76dcae7ef#tail-->","link":"https://www.music-flo.com/detail/album/edzhoalaz/albumtrack","retrieved":1635478882829},{"title":"아버지 (Original Song by 인순이)","contents":"<!--fragment#166e209a946#head-->NIDA<!--fragment#166e209a946#tail-->","link":"https://www.music-flo.com/detail/album/edzhozyoo/albumtrack","retrieved":1635414018815},{"title":"obsession","contents":"<!--fragment#b5b8baee65#head-->웨일<!--fragment#b5b8baee65#tail-->","link":"https://www.music-flo.com/detail/album/edzhlehed/albumtrack","retrieved":1635414018763},{"title":"초행","contents":"<!--fragment#919d3cd0bd#head-->신유<!--fragment#919d3cd0bd#tail-->","link":"https://www.music-flo.com/detail/album/edzhoahyd/albumtrack","retrieved":1635414018767},{"title":"Dream Land","contents":"<!--fragment#eceac4372e#head-->김현우<!--fragment#eceac4372e#tail-->","link":"https://www.music-flo.com/detail/album/edzhllyal/albumtrack","retrieved":1635414018764},{"title":"속이 궁금해 (아는 여자애 X 데이브레이크, 유키카)","contents":"<!--fragment#9665e98629#head-->데이브레이크 (DAYBREAK)<!--fragment#9665e98629#tail-->","link":"https://www.music-flo.com/detail/album/edzhzzaez/albumtrack","retrieved":1635392452651},{"title":"4EVeR [Prod. JINex]","contents":"<!--fragment#5e2dc3f207#head-->마샬 (MRSHLL)<!--fragment#5e2dc3f207#tail-->","link":"https://www.music-flo.com/detail/album/edzhoayha/albumtrack","retrieved":1635414018770},{"title":"낙하산은 펴지 않을게요","contents":"<!--fragment#103c8637240#head-->극한데뷔 야생돌<!--fragment#103c8637240#tail-->","link":"https://www.music-flo.com/detail/album/edzhollah/albumtrack","retrieved":1635392452667},{"title":"파랑새","contents":"<!--fragment#15b5bd15c90#head-->이제<!--fragment#15b5bd15c90#tail-->","link":"https://www.music-flo.com/detail/album/edzhliyoz/albumtrack","retrieved":1635392452666},{"title":"Yellow (Feat. 이영빈)","contents":"<!--fragment#1241d2b6c8b#head-->CIELOGROOVE (씨엘로그루브)<!--fragment#1241d2b6c8b#tail-->","link":"https://www.music-flo.com/detail/album/edzhzldhn/albumtrack","retrieved":1635392452662},{"title":"Cliché","contents":"<!--fragment#6a098ec359#head-->XINSAYNE<!--fragment#6a098ec359#tail-->","link":"https://www.music-flo.com/detail/album/edzhelyaa/albumtrack","retrieved":1635414018775},{"title":"DANCE2 (Feat. Ja Mezz)","contents":"<!--fragment#e06a160068#head-->8F<!--fragment#e06a160068#tail-->","link":"https://www.music-flo.com/detail/album/edzhlldly/albumtrack","retrieved":1635414018780},{"title":"가르치지마","contents":"<!--fragment#c6e5f02461#head-->에일리(Ailee)<!--fragment#c6e5f02461#tail-->","link":"https://www.music-flo.com/detail/album/edzhzdddn/albumtrack","retrieved":1635327629594},{"title":"이 밤에 취해 (With noovv)","contents":"<!--fragment#957bfdfe23#head-->SUDI<!--fragment#957bfdfe23#tail-->","link":"https://www.music-flo.com/detail/album/edzhinydi/albumtrack","retrieved":1635392452668},{"title":"BAD GIRL (Prod. Czaer)","contents":"<!--fragment#b560a11fd2#head-->라치카 (LACHICA)<!--fragment#b560a11fd2#tail-->","link":"https://www.music-flo.com/detail/album/edzhleonl/albumtrack","retrieved":1635327629598},{"title":"미워지지가 않아 (Unhateable)","contents":"<!--fragment#13085c536dd#head-->노을<!--fragment#13085c536dd#tail-->","link":"https://www.music-flo.com/detail/album/edzhlznne/albumtrack","retrieved":1635327629595},{"title":"발냄새 with 육중완","contents":"<!--fragment#fe0e72a7e9#head-->소욘<!--fragment#fe0e72a7e9#tail-->","link":"https://www.music-flo.com/detail/album/edzhaydhy/albumtrack","retrieved":1635414018771},{"title":"Clarity","contents":"<!--fragment#c3fb1ff4a9#head-->로예 (LOHYE)<!--fragment#c3fb1ff4a9#tail-->","link":"https://www.music-flo.com/detail/album/edzhoanho/albumtrack","retrieved":1635392452619},{"title":"Knocking On","contents":"<!--fragment#119bb59bfd7#head-->Janet Suhh (자넷서)<!--fragment#119bb59bfd7#tail-->","link":"https://www.music-flo.com/detail/album/edzhoadoy/albumtrack","retrieved":1635392452612},{"title":"환절기 (Early October)","contents":"<!--fragment#c20da1c6ea#head-->종한 (JONGHAN)<!--fragment#c20da1c6ea#tail-->","link":"https://www.music-flo.com/detail/album/edzhloini/albumtrack","retrieved":1635392452613},{"title":"PLASTIC CITY","contents":"<!--fragment#14e4d22e1f0#head-->ESTi<!--fragment#14e4d22e1f0#tail-->","link":"https://www.music-flo.com/detail/album/edzhlhonl/albumtrack","retrieved":1635392452612},{"title":"여우같아 넌 (Feat. GIST)","contents":"<!--fragment#5f9d093ac5#head-->미카엘 (M!KYLE)<!--fragment#5f9d093ac5#tail-->","link":"https://www.music-flo.com/detail/album/edzhildal/albumtrack","retrieved":1635392452613},{"title":"고백","contents":"<!--fragment#4807b9aef0#head-->하범석<!--fragment#4807b9aef0#tail-->","link":"https://www.music-flo.com/detail/album/edzhzldio/albumtrack","retrieved":1635392452628},{"title":"Aim","contents":"<!--fragment#4c8a4e4a8d#head-->Webley (웨블리)<!--fragment#4c8a4e4a8d#tail-->","link":"https://www.music-flo.com/detail/album/edzhlhono/albumtrack","retrieved":1635392452632},{"title":"치즈버거 블루스 (최항석과 부기몬스터X배달의민족)","contents":"<!--fragment#e4da5bab8e#head-->최항석과 부기몬스터<!--fragment#e4da5bab8e#tail-->","link":"https://www.music-flo.com/detail/album/edzhloyzz/albumtrack","retrieved":1635392452621},{"title":"Hum","contents":"<!--fragment#f993ae15e6#head-->어텀 (Autumn)<!--fragment#f993ae15e6#tail-->","link":"https://www.music-flo.com/detail/album/edzhleola/albumtrack","retrieved":1635392452614},{"title":"불토(Fire Saturday)","contents":"<!--fragment#13a6d99bb16#head-->SECRET NUMBER (시크릿넘버)<!--fragment#13a6d99bb16#tail-->","link":"https://www.music-flo.com/detail/album/edzhlznni/albumtrack","retrieved":1635327629600},{"title":"그대가 있기에","contents":"<!--fragment#ceff7e7726#head-->차서원<!--fragment#ceff7e7726#tail-->","link":"https://www.music-flo.com/detail/album/edzhlhzzh/albumtrack","retrieved":1635392452628},{"title":"Wondering","contents":"<!--fragment#8eb8919f75#head-->CHAI (이수정)<!--fragment#8eb8919f75#tail-->","link":"https://www.music-flo.com/detail/album/edzhlhold/albumtrack","retrieved":1635327629601},{"title":"지워야해","contents":"<!--fragment#173ee9ed798#head-->코마제이 (Komah Jay)<!--fragment#173ee9ed798#tail-->","link":"https://www.music-flo.com/detail/album/edzhoaaee/albumtrack","retrieved":1635392452631},{"title":"달 크레이터","contents":"<!--fragment#5e3e12cf46#head-->김예지<!--fragment#5e3e12cf46#tail-->","link":"https://www.music-flo.com/detail/album/edzhlhony/albumtrack","retrieved":1635327629604},{"title":"TICK TOCK","contents":"<!--fragment#e7131f2769#head-->JUST B (저스트비)<!--fragment#e7131f2769#tail-->","link":"https://www.music-flo.com/detail/album/edzhllhdh/albumtrack","retrieved":1635327629603},{"title":"인스타그만 (Feat. Touch the Sky)","contents":"<!--fragment#1492979b6ab#head-->황세현 (h3hyeon)<!--fragment#1492979b6ab#tail-->","link":"https://www.music-flo.com/detail/album/edzhzelye/albumtrack","retrieved":1635306050413},{"title":"Not Friends (ALAWN REMIX)","contents":"<!--fragment#35089d2a1c#head-->이달의 소녀<!--fragment#35089d2a1c#tail-->","link":"https://www.music-flo.com/detail/album/edzhlozoe/albumtrack","retrieved":1635306050408},{"title":"shall we dance?","contents":"<!--fragment#dca4790fdc#head-->칠리 (chilly)<!--fragment#dca4790fdc#tail-->","link":"https://www.music-flo.com/detail/album/edzhlezee/albumtrack","retrieved":1635327629510},{"title":"Villain","contents":"<!--fragment#f9b4cdaf2a#head-->에이프릴 세컨드 (April 2nd)<!--fragment#f9b4cdaf2a#tail-->","link":"https://www.music-flo.com/detail/album/edzohozao/albumtrack","retrieved":1635327629510},{"title":"우린 노래가 될까","contents":"<!--fragment#f9e28070de#head-->너드커넥션 (Nerd Connection)<!--fragment#f9e28070de#tail-->","link":"https://www.music-flo.com/detail/album/edzhledaa/albumtrack","retrieved":1635306050415},{"title":"나비효과","contents":"<!--fragment#3fff89a377#head-->볼빨간사춘기<!--fragment#3fff89a377#tail-->","link":"https://www.music-flo.com/detail/album/edzhelzde/albumtrack","retrieved":1635241434564},{"title":"사랑이 시작된 거야 (Vocal. 정미, 이윤주)","contents":"<!--fragment#f0ea3aa556#head-->Iony (아이오니)<!--fragment#f0ea3aa556#tail-->","link":"https://www.music-flo.com/detail/album/edzhleloy/albumtrack","retrieved":1635327629511},{"title":"안녕 나야","contents":"<!--fragment#40f1329254#head-->장의수<!--fragment#40f1329254#tail-->","link":"https://www.music-flo.com/detail/album/edzheziyy/albumtrack","retrieved":1635306050409},{"title":"아무 말도 필요 없어 (Feat. 최희서)","contents":"<!--fragment#127849ce4c3#head-->박인영<!--fragment#127849ce4c3#tail-->","link":"https://www.music-flo.com/detail/album/edzheeilh/albumtrack","retrieved":1635327629511},{"title":"Party! (have a good time)","contents":"<!--fragment#1767f6b781e#head-->KINIE.K (키니케이)<!--fragment#1767f6b781e#tail-->","link":"https://www.music-flo.com/detail/album/edzhlhozl/albumtrack","retrieved":1635327629511},{"title":"Lisianthus (Song By NISSI, Chaanill) (Prod. 플라스틱 케이스)","contents":"<!--fragment#4e0c258027#head-->KozyPop<!--fragment#4e0c258027#tail-->","link":"https://www.music-flo.com/detail/album/edzhliyhy/albumtrack","retrieved":1635306050427},{"title":"짝사랑","contents":"<!--fragment#10f32d27a8#head-->소리맵시<!--fragment#10f32d27a8#tail-->","link":"https://www.music-flo.com/detail/album/edzhloaod/albumtrack","retrieved":1635306050415},{"title":"그리워 그리워","contents":"<!--fragment#21712a1d35#head-->이예준<!--fragment#21712a1d35#tail-->","link":"https://www.music-flo.com/detail/album/edzheznie/albumtrack","retrieved":1635241434564},{"title":"I Was Called Parasite, U Call Me Paradise","contents":"<!--fragment#17432dbdf8e#head-->moOon<!--fragment#17432dbdf8e#tail-->","link":"https://www.music-flo.com/detail/album/edzhlehoh/albumtrack","retrieved":1635306050284},{"title":"제자리로","contents":"<!--fragment#3f99ce76d2#head-->김기쁨<!--fragment#3f99ce76d2#tail-->","link":"https://www.music-flo.com/detail/album/edzhlozln/albumtrack","retrieved":1635306050285},{"title":"먼밤, 나는 아직도","contents":"<!--fragment#112c5a43fb0#head-->경미<!--fragment#112c5a43fb0#tail-->","link":"https://www.music-flo.com/detail/album/edzhliyoh/albumtrack","retrieved":1635306050284},{"title":"선물","contents":"<!--fragment#1171fdba32e#head-->SOLE (쏠)<!--fragment#1171fdba32e#tail-->","link":"https://www.music-flo.com/detail/album/edzhnyezy/albumtrack","retrieved":1635241434565},{"title":"Do 4 Me","contents":"<!--fragment#15ba842c499#head-->EPEX (이펙스)<!--fragment#15ba842c499#tail-->","link":"https://www.music-flo.com/detail/album/edzheelye/albumtrack","retrieved":1635241434567},{"title":"Later...","contents":"<!--fragment#1548db33bf9#head-->지환<!--fragment#1548db33bf9#tail-->","link":"https://www.music-flo.com/detail/album/edzhledll/albumtrack","retrieved":1635306050285},{"title":"지는 날","contents":"<!--fragment#119503009af#head-->그네<!--fragment#119503009af#tail-->","link":"https://www.music-flo.com/detail/album/edzhezlon/albumtrack","retrieved":1635306050285},{"title":"GHOST","contents":"<!--fragment#165cd5f5fd#head-->드림노트 (DreamNote)<!--fragment#165cd5f5fd#tail-->","link":"https://www.music-flo.com/detail/album/edzhlioid/albumtrack","retrieved":1635241434566},{"title":"Need U Right Now","contents":"<!--fragment#10d6b18ae02#head-->Bluelk (블루엘크)<!--fragment#10d6b18ae02#tail-->","link":"https://www.music-flo.com/detail/album/edzhelzle/albumtrack","retrieved":1635306050325},{"title":"The Nation","contents":"<!--fragment#d39ded6183#head-->PITTA (강형호)<!--fragment#d39ded6183#tail-->","link":"https://www.music-flo.com/detail/album/edzhenyna/albumtrack","retrieved":1635219657699},{"title":"사랑의 온도 (Feat. 퀸샤(Quinsha))","contents":"<!--fragment#15d02b70192#head-->재덕 (JD)<!--fragment#15d02b70192#tail-->","link":"https://www.music-flo.com/detail/album/edzhniyay/albumtrack","retrieved":1635306050327},{"title":"Elena Coda (Feat. 일레인)","contents":"<!--fragment#1784318fed7#head-->015B<!--fragment#1784318fed7#tail-->","link":"https://www.music-flo.com/detail/album/edzhelyan/albumtrack","retrieved":1635219657695},{"title":"좋아한단 말로 전해 [Feat. 로화 (ROHWA)]","contents":"<!--fragment#159becdc5a5#head-->양혁<!--fragment#159becdc5a5#tail-->","link":"https://www.music-flo.com/detail/album/edzhellzy/albumtrack","retrieved":1635241434489},{"title":"HORIZON LINE (Feat. Cherry Coke)","contents":"<!--fragment#d192f64ca2#head-->Jvde Milez (주드 마일즈)<!--fragment#d192f64ca2#tail-->","link":"https://www.music-flo.com/detail/album/edzheinnz/albumtrack","retrieved":1635241434489},{"title":"Lovesong (Feat. 수연이)","contents":"<!--fragment#177668f132#head-->seshin<!--fragment#177668f132#tail-->","link":"https://www.music-flo.com/detail/album/edzznnaho/albumtrack","retrieved":1635241434494},{"title":"IF I","contents":"<!--fragment#11f4394fd42#head-->백지영<!--fragment#11f4394fd42#tail-->","link":"https://www.music-flo.com/detail/album/edzheznil/albumtrack","retrieved":1635219657699},{"title":"HOME","contents":"<!--fragment#9e0418b031#head-->SEO SANG JUNE<!--fragment#9e0418b031#tail-->","link":"https://www.music-flo.com/detail/album/edzhindne/albumtrack","retrieved":1635241434501},{"title":"안녕이 늦어서 미안해","contents":"<!--fragment#7e54581363#head-->디에이드 (The Ade)<!--fragment#7e54581363#tail-->","link":"https://www.music-flo.com/detail/album/edzhelehh/albumtrack","retrieved":1635219657627},{"title":"Glow","contents":"<!--fragment#4e4572c9f6#head-->Jimmy Brown<!--fragment#4e4572c9f6#tail-->","link":"https://www.music-flo.com/detail/album/edzhndlnl/albumtrack","retrieved":1635219657723},{"title":"꼼짝마","contents":"<!--fragment#3605465791#head-->SOMYA (소먀)<!--fragment#3605465791#tail-->","link":"https://www.music-flo.com/detail/album/edzhihloe/albumtrack","retrieved":1635306050340},{"title":"바다","contents":"<!--fragment#100f0b60326#head-->초승 (CHOSNG)<!--fragment#100f0b60326#tail-->","link":"https://www.music-flo.com/detail/album/edzhezeez/albumtrack","retrieved":1635219657622}]}