{"title":"FLO ─ New Track","url":"https://www.music-flo.com/new/track?sortType=KPOP","favicon":"https://www.music-flo.com/favicon.ico","elements":[{"title":"LOCO","contents":"<!--fragment#7207951e67#head-->ITZY (있지)<!--fragment#7207951e67#tail-->","link":"https://www.music-flo.com/detail/album/edzlondzy/albumtrack","retrieved":1632458967744,"image":"https://cdn.music-flo.com/image/v2/album/069/572/06/04/406572069_614c33eb_s.jpg?1632383981585/dims/resize/140x140/quality/90"},{"title":"9월 24일","contents":"<!--fragment#dd23cf9e46#head-->임한별<!--fragment#dd23cf9e46#tail-->","link":"https://www.music-flo.com/detail/album/edzlonnzi/albumtrack","retrieved":1632476358678,"image":"https://cdn.music-flo.com/image/v2/album/263/572/06/04/406572263_614c4494_s.jpg?1632388247367/dims/resize/140x140/quality/90"},{"title":"외로워","contents":"<!--fragment#d8cdfcd1cb#head-->김사월<!--fragment#d8cdfcd1cb#tail-->","link":"https://www.music-flo.com/detail/album/edzleyzno/albumtrack","retrieved":1632476358682,"image":"https://cdn.music-flo.com/image/v2/album/627/549/06/04/406549627_6140423b_s.jpg?1631601212289/dims/resize/140x140/quality/90"},{"title":"Problem","contents":"<!--fragment#a44cfd406b#head-->이츠<!--fragment#a44cfd406b#tail-->","link":"https://www.music-flo.com/detail/album/edzloeayo/albumtrack","retrieved":1632476358683,"image":"https://cdn.music-flo.com/image/v2/album/197/574/06/04/406574197_614d22ef_s.jpg?1632445169447/dims/resize/140x140/quality/90"},{"title":"RED ALERT","contents":"<!--fragment#80b398a313#head-->리듬파워<!--fragment#80b398a313#tail-->","link":"https://www.music-flo.com/detail/album/edzlllahy/albumtrack","retrieved":1632476358684,"image":"https://cdn.music-flo.com/image/v2/album/189/555/06/04/406555189_6142a2ef_s.jpg?1631757044262/dims/resize/140x140/quality/90"},{"title":"침대열차 (Train Bed) (Feat. 범키)","contents":"<!--fragment#123b806c50c#head-->키비 (Kebee)<!--fragment#123b806c50c#tail-->","link":"https://www.music-flo.com/detail/album/edzllheie/albumtrack","retrieved":1632476358684,"image":"https://cdn.music-flo.com/image/v2/album/434/558/06/04/406558434_614d3588_s.jpg?1632449932378/dims/resize/140x140/quality/90"},{"title":"던(DUN)","contents":"<!--fragment#d5190dbeb8#head-->정민<!--fragment#d5190dbeb8#tail-->","link":"https://www.music-flo.com/detail/album/edzllhhyl/albumtrack","retrieved":1632476358685,"image":"https://cdn.music-flo.com/image/v2/album/895/558/06/04/406558895_61442221_o.jpg?1631855137802/dims/resize/140/quality/90"},{"title":"Perfume (Song By Owler, Austn) (Prod. SIM2)","contents":"<!--fragment#11f58e7b09b#head-->KozyPop<!--fragment#11f58e7b09b#tail-->","link":"https://www.music-flo.com/detail/album/edzloaynh/albumtrack","retrieved":1632476358586},{"title":"Hutari (Feat. Gatti, Make A Movie)","contents":"<!--fragment#5506052fc8#head-->Santa Paine<!--fragment#5506052fc8#tail-->","link":"https://www.music-flo.com/detail/album/edzllhloa/albumtrack","retrieved":1632476358590},{"title":"한 걸음 더","contents":"<!--fragment#344f7abb7e#head-->천단비<!--fragment#344f7abb7e#tail-->","link":"https://www.music-flo.com/detail/album/edzloahoi/albumtrack","retrieved":1632476358591},{"title":"사랑하지 않을 이유는 없다","contents":"<!--fragment#15bba6f4329#head-->HD BL4CK<!--fragment#15bba6f4329#tail-->","link":"https://www.music-flo.com/detail/album/edzlllldy/albumtrack","retrieved":1632476358598},{"title":"여전히 아름다운지 (Drama Ver.)","contents":"<!--fragment#1406b2ef65f#head-->미도와 파라솔<!--fragment#1406b2ef65f#tail-->","link":"https://www.music-flo.com/detail/album/edzloaeid/albumtrack","retrieved":1632454832643},{"title":"Priceless","contents":"<!--fragment#1210d3b338d#head-->Dolo<!--fragment#1210d3b338d#tail-->","link":"https://www.music-flo.com/detail/album/edzllheil/albumtrack","retrieved":1632454832499},{"title":"TULIP","contents":"<!--fragment#137f10252e1#head-->BACKGOO<!--fragment#137f10252e1#tail-->","link":"https://www.music-flo.com/detail/album/edzllnlnz/albumtrack","retrieved":1632476358605},{"title":"그날 찬란했던 우리 (feat.다무)","contents":"<!--fragment#e7164d47ab#head-->톤 (TONE)<!--fragment#e7164d47ab#tail-->","link":"https://www.music-flo.com/detail/album/edzloahyh/albumtrack","retrieved":1632454832605},{"title":"True Romance","contents":"<!--fragment#a3d22bc0de#head-->크루셜스타 (CRUCiAL STAR)<!--fragment#a3d22bc0de#tail-->","link":"https://www.music-flo.com/detail/album/edzllhhih/albumtrack","retrieved":1632454832645},{"title":"River Flows In You","contents":"<!--fragment#8aea8bbe2c#head-->이루마<!--fragment#8aea8bbe2c#tail-->","link":"https://www.music-flo.com/detail/album/edzlzohlz/albumtrack","retrieved":1632454832641},{"title":"이밤에","contents":"<!--fragment#13be135c2c5#head-->Adios Audio<!--fragment#13be135c2c5#tail-->","link":"https://www.music-flo.com/detail/album/edzlelyhy/albumtrack","retrieved":1632454832493},{"title":"휘휘(Hwi Hwi)","contents":"<!--fragment#16a6e44606b#head-->하얀 (HAYAN)<!--fragment#16a6e44606b#tail-->","link":"https://www.music-flo.com/detail/album/edzllydzy/albumtrack","retrieved":1632454832503},{"title":"가을 상자 (With 이석훈)","contents":"<!--fragment#3c871a03f6#head-->조유리<!--fragment#3c871a03f6#tail-->","link":"https://www.music-flo.com/detail/album/edzloaelo/albumtrack","retrieved":1632389983247},{"title":"기타로 오토바이를 타자","contents":"<!--fragment#7bc4ac7e18#head-->소울맨<!--fragment#7bc4ac7e18#tail-->","link":"https://www.music-flo.com/detail/album/edzllzydz/albumtrack","retrieved":1632454832646},{"title":"그리움 축제","contents":"<!--fragment#70d9f33225#head-->윤종신<!--fragment#70d9f33225#tail-->","link":"https://www.music-flo.com/detail/album/edzloahzh/albumtrack","retrieved":1632389983245},{"title":"그대와 함께한 내 모든 날들이 (Feat. 리디아)","contents":"<!--fragment#8d1ded4bc1#head-->슈슈가<!--fragment#8d1ded4bc1#tail-->","link":"https://www.music-flo.com/detail/album/edzlllohy/albumtrack","retrieved":1632454832501},{"title":"후회가 돼","contents":"<!--fragment#3f7bf441d7#head-->리즈 (Leeds)<!--fragment#3f7bf441d7#tail-->","link":"https://www.music-flo.com/detail/album/edzllzldi/albumtrack","retrieved":1632454832497},{"title":"너의 세계로 (Let Me In)","contents":"<!--fragment#c2ef601373#head-->우주소녀<!--fragment#c2ef601373#tail-->","link":"https://www.music-flo.com/detail/album/edzloaeiz/albumtrack","retrieved":1632389983246},{"title":"even if (Prod. By edenbyeden)","contents":"<!--fragment#11e64823c08#head-->H:SEAN<!--fragment#11e64823c08#tail-->","link":"https://www.music-flo.com/detail/album/edzllnlni/albumtrack","retrieved":1632454832519},{"title":"사망가 (studio live ver.)","contents":"<!--fragment#4e6b430f98#head-->크라잉넛 (CRYING NUT)<!--fragment#4e6b430f98#tail-->","link":"https://www.music-flo.com/detail/album/edzlondyh/albumtrack","retrieved":1632454832607},{"title":"어떻게 지내시나요","contents":"<!--fragment#cc88e971e#head-->프리티브라운<!--fragment#cc88e971e#tail-->","link":"https://www.music-flo.com/detail/album/edzllzall/albumtrack","retrieved":1632389983194},{"title":"TOO DIRTY (feat. 스카이민혁, Klutch, 딥플로우)","contents":"<!--fragment#81c64c470d#head-->IndEgo Aid<!--fragment#81c64c470d#tail-->","link":"https://www.music-flo.com/detail/album/edzllzlyd/albumtrack","retrieved":1632454832505},{"title":"고민은 배송만 늦출 뿐","contents":"<!--fragment#15eaed31d06#head-->노라조<!--fragment#15eaed31d06#tail-->","link":"https://www.music-flo.com/detail/album/edzllzyhe/albumtrack","retrieved":1632389983253},{"title":"보고 싶어라","contents":"<!--fragment#f2d9732cba#head-->섬의 편지<!--fragment#f2d9732cba#tail-->","link":"https://www.music-flo.com/detail/album/edzllnala/albumtrack","retrieved":1632454832508},{"title":"Something (Feat. Meego, BIG Naughty (서동현))","contents":"<!--fragment#11a30bd60f#head-->dress<!--fragment#11a30bd60f#tail-->","link":"https://www.music-flo.com/detail/album/edzloaazi/albumtrack","retrieved":1632389983252},{"title":"이 슬픔이 멈추길","contents":"<!--fragment#148e91f3e83#head-->Ujin<!--fragment#148e91f3e83#tail-->","link":"https://www.music-flo.com/detail/album/edzlzzndd/albumtrack","retrieved":1632389983198},{"title":"Love You","contents":"<!--fragment#d1d3ee99b#head-->조범진<!--fragment#d1d3ee99b#tail-->","link":"https://www.music-flo.com/detail/album/edzloahzy/albumtrack","retrieved":1632454832519},{"title":"CHRISTIAN DIOR (Feat. Octavian)","contents":"<!--fragment#14c086b1e40#head-->Chillin Homie<!--fragment#14c086b1e40#tail-->","link":"https://www.music-flo.com/detail/album/edzlodzyo/albumtrack","retrieved":1632389983281},{"title":"하루 끝","contents":"<!--fragment#d58abea178#head-->해빈<!--fragment#d58abea178#tail-->","link":"https://www.music-flo.com/detail/album/edzllzhnd/albumtrack","retrieved":1632372604131},{"title":"Paris With You (Feat. Jae Luna)","contents":"<!--fragment#aa0751a1c2#head-->서액터<!--fragment#aa0751a1c2#tail-->","link":"https://www.music-flo.com/detail/album/edzllhhzi/albumtrack","retrieved":1632372604149},{"title":"선영과 진우","contents":"<!--fragment#b0168b8e96#head-->류석원<!--fragment#b0168b8e96#tail-->","link":"https://www.music-flo.com/detail/album/edzllnlin/albumtrack","retrieved":1632389983197},{"title":"Framed","contents":"<!--fragment#177915f2a68#head-->Kevin Park<!--fragment#177915f2a68#tail-->","link":"https://www.music-flo.com/detail/album/edzlleozd/albumtrack","retrieved":1632389983197},{"title":"내 옆에는 너만 있었으면 해","contents":"<!--fragment#113c9b79270#head-->함연지<!--fragment#113c9b79270#tail-->","link":"https://www.music-flo.com/detail/album/edzllhlai/albumtrack","retrieved":1632372604150},{"title":"알았더라면","contents":"<!--fragment#11dd978c983#head-->우은미<!--fragment#11dd978c983#tail-->","link":"https://www.music-flo.com/detail/album/edzlledoo/albumtrack","retrieved":1632372604160},{"title":"이 생애 우리 다시 (연화 X RENDY)","contents":"<!--fragment#1551a87d191#head-->RENDY (렌디)<!--fragment#1551a87d191#tail-->","link":"https://www.music-flo.com/detail/album/edzllzhhi/albumtrack","retrieved":1632372604161},{"title":"RAT A TAT","contents":"<!--fragment#33cec068dd#head-->뷰티박스 (BEAUTY BOX)<!--fragment#33cec068dd#tail-->","link":"https://www.music-flo.com/detail/album/edzllodnz/albumtrack","retrieved":1632372604111},{"title":"Routine","contents":"<!--fragment#10fa6328bd0#head-->아녹 (Anoc)<!--fragment#10fa6328bd0#tail-->","link":"https://www.music-flo.com/detail/album/edzlzezze/albumtrack","retrieved":1632372604151},{"title":"밤워크","contents":"<!--fragment#422be2f182#head-->양창근<!--fragment#422be2f182#tail-->","link":"https://www.music-flo.com/detail/album/edzllnlnl/albumtrack","retrieved":1632372604151},{"title":"너를 생각해","contents":"<!--fragment#e837e6979#head-->주시크 (Joosiq)<!--fragment#e837e6979#tail-->","link":"https://www.music-flo.com/detail/album/edzllnlii/albumtrack","retrieved":1632303544758},{"title":"Want Love","contents":"<!--fragment#162b33bd044#head-->MOTIP<!--fragment#162b33bd044#tail-->","link":"https://www.music-flo.com/detail/album/edzllzoed/albumtrack","retrieved":1632372604073},{"title":"극복 (feat. DJ Use-up, Gokim, Smoozee, Vimoka)","contents":"<!--fragment#5959b5a8ba#head-->원썬<!--fragment#5959b5a8ba#tail-->","link":"https://www.music-flo.com/detail/album/edzllzedh/albumtrack","retrieved":1632372604106},{"title":"I Miss You","contents":"<!--fragment#5633e965a3#head-->비비안<!--fragment#5633e965a3#tail-->","link":"https://www.music-flo.com/detail/album/edzllneny/albumtrack","retrieved":1632372604111},{"title":"해운대","contents":"<!--fragment#70bcde07f0#head-->순순희<!--fragment#70bcde07f0#tail-->","link":"https://www.music-flo.com/detail/album/edzllhoyy/albumtrack","retrieved":1632303544758},{"title":"yesweare","contents":"<!--fragment#102a649292a#head-->안0김박재재<!--fragment#102a649292a#tail-->","link":"https://www.music-flo.com/detail/album/edzleleel/albumtrack","retrieved":1632372604107},{"title":"보고 싶었어 가을 (금혼령 X 한동근)","contents":"<!--fragment#a3d1c151cc#head-->한동근<!--fragment#a3d1c151cc#tail-->","link":"https://www.music-flo.com/detail/album/edzllneah/albumtrack","retrieved":1632303544759},{"title":"ROCK STEADY (Feat. 넋업샨 (NUCK), DJ EBONY)","contents":"<!--fragment#176f935626d#head-->알이에스티 (R-EST)<!--fragment#176f935626d#tail-->","link":"https://www.music-flo.com/detail/album/edzlllzen/albumtrack","retrieved":1632372604109},{"title":"달빛 경주","contents":"<!--fragment#11c854067e1#head-->조성모<!--fragment#11c854067e1#tail-->","link":"https://www.music-flo.com/detail/album/edzllnoll/albumtrack","retrieved":1632303544759},{"title":"Slowride","contents":"<!--fragment#ca15475f62#head-->CHS<!--fragment#ca15475f62#tail-->","link":"https://www.music-flo.com/detail/album/edzllliei/albumtrack","retrieved":1632372604111},{"title":"그대 없는 밤 (Vocal by YEOUL(한여울))","contents":"<!--fragment#4a67e9f7b9#head-->제이크오 (Jake.O)<!--fragment#4a67e9f7b9#tail-->","link":"https://www.music-flo.com/detail/album/edzllnnhd/albumtrack","retrieved":1632372604111},{"title":"Sin City","contents":"<!--fragment#14b3b0070eb#head-->Royal 44<!--fragment#14b3b0070eb#tail-->","link":"https://www.music-flo.com/detail/album/edzllondd/albumtrack","retrieved":1632303544773},{"title":"바보","contents":"<!--fragment#df439c1c89#head-->동현<!--fragment#df439c1c89#tail-->","link":"https://www.music-flo.com/detail/album/edzllldoi/albumtrack","retrieved":1632372604112},{"title":"Get Enough","contents":"<!--fragment#6ebfda51fd#head-->Blase (블라세)<!--fragment#6ebfda51fd#tail-->","link":"https://www.music-flo.com/detail/album/edzllnedl/albumtrack","retrieved":1632303544773},{"title":"나는 너에게","contents":"<!--fragment#122724a191#head-->윤원<!--fragment#122724a191#tail-->","link":"https://www.music-flo.com/detail/album/edzllliye/albumtrack","retrieved":1632286305629},{"title":"우리가 왜 헤어져 (Feat. 전은진)","contents":"<!--fragment#166570483f3#head-->새벽창문<!--fragment#166570483f3#tail-->","link":"https://www.music-flo.com/detail/album/edzllhoih/albumtrack","retrieved":1632286305629},{"title":"One more dance! (Song by 하웅(Hawoong), SIM2)","contents":"<!--fragment#5aaf05e32d#head-->SOUND PALETTE<!--fragment#5aaf05e32d#tail-->","link":"https://www.music-flo.com/detail/album/edzllzlni/albumtrack","retrieved":1632286305651},{"title":"Strawberry Lips (Explicit Ver.)","contents":"<!--fragment#7a022aeb60#head-->DEUL<!--fragment#7a022aeb60#tail-->","link":"https://www.music-flo.com/detail/album/edzlznzol/albumtrack","retrieved":1632303544707},{"title":"parjun&macgirly(파전&막걸리)","contents":"<!--fragment#28ab304153#head-->릴 보이스피싱<!--fragment#28ab304153#tail-->","link":"https://www.music-flo.com/detail/album/edzllneyo/albumtrack","retrieved":1632303544708},{"title":"참 사랑했었는데","contents":"<!--fragment#eaf9ae19d2#head-->모닝커피 (Morning Coffee)<!--fragment#eaf9ae19d2#tail-->","link":"https://www.music-flo.com/detail/album/edzllzhen/albumtrack","retrieved":1632286305658},{"title":"한걸음 더","contents":"<!--fragment#2841b04fd6#head-->미소 (DreamNote)<!--fragment#2841b04fd6#tail-->","link":"https://www.music-flo.com/detail/album/edzllneho/albumtrack","retrieved":1632286305603},{"title":"Day By Day","contents":"<!--fragment#2f7f9a5a0f#head-->24아워즈 (24Hours)<!--fragment#2f7f9a5a0f#tail-->","link":"https://www.music-flo.com/detail/album/edzllnnoh/albumtrack","retrieved":1632286305656},{"title":"별빛 같은 나의 사랑아","contents":"<!--fragment#8ec2b6427b#head-->임영웅<!--fragment#8ec2b6427b#tail-->","link":"https://www.music-flo.com/detail/album/edzlloaoo/albumtrack","retrieved":1632217176376},{"title":"JOGGERPANTS","contents":"<!--fragment#153ba3a6213#head-->비치보이스 (The Beach Voice)<!--fragment#153ba3a6213#tail-->","link":"https://www.music-flo.com/detail/album/edzllzlyn/albumtrack","retrieved":1632286305603},{"title":"살짝궁 니 맘 들켰지?","contents":"<!--fragment#2738f4df78#head-->유정식<!--fragment#2738f4df78#tail-->","link":"https://www.music-flo.com/detail/album/edzleoydn/albumtrack","retrieved":1632286305652},{"title":"그리운 밤 보고픈 밤 (feat.디어밍)","contents":"<!--fragment#7415ad7b01#head-->에피타이저 (Appetizer)<!--fragment#7415ad7b01#tail-->","link":"https://www.music-flo.com/detail/album/edzllnihz/albumtrack","retrieved":1632217176384},{"title":"Stay With Me","contents":"<!--fragment#e85485e601#head-->김예준<!--fragment#e85485e601#tail-->","link":"https://www.music-flo.com/detail/album/edzllleza/albumtrack","retrieved":1632286305603},{"title":"외롭지 않다면 사랑에 빠질 수 없지 않나요 (Prod. midsummer)","contents":"<!--fragment#2356480a52#head-->개미친구 (gamichingoo)<!--fragment#2356480a52#tail-->","link":"https://www.music-flo.com/detail/album/edzllllnn/albumtrack","retrieved":1632286305603},{"title":"slide (feat. GIST)","contents":"<!--fragment#75aea9c346#head-->CMBY (코마보이)<!--fragment#75aea9c346#tail-->","link":"https://www.music-flo.com/detail/album/edzllnili/albumtrack","retrieved":1632217176385},{"title":"xo","contents":"<!--fragment#17a83244564#head-->G. Nine<!--fragment#17a83244564#tail-->","link":"https://www.music-flo.com/detail/album/edzllnail/albumtrack","retrieved":1632217176387},{"title":"희나리","contents":"<!--fragment#ab5251165a#head-->임영웅<!--fragment#ab5251165a#tail-->","link":"https://www.music-flo.com/detail/album/edzllhzyi/albumtrack","retrieved":1632195622926},{"title":"타령 모음곡","contents":"<!--fragment#f97a617013#head-->양지은<!--fragment#f97a617013#tail-->","link":"https://www.music-flo.com/detail/album/edzllhizi/albumtrack","retrieved":1632195622931},{"title":"Ready For Your Love","contents":"<!--fragment#1070485daec#head-->Kriz<!--fragment#1070485daec#tail-->","link":"https://www.music-flo.com/detail/album/edzllneln/albumtrack","retrieved":1632195622931},{"title":"Beside You (With Lokid, 여유정)","contents":"<!--fragment#520032b881#head-->SIM2<!--fragment#520032b881#tail-->","link":"https://www.music-flo.com/detail/album/edzlzazde/albumtrack","retrieved":1632195622931},{"title":"BRAIN","contents":"<!--fragment#6ae2349849#head-->양요섭<!--fragment#6ae2349849#tail-->","link":"https://www.music-flo.com/detail/album/edzllonnl/albumtrack","retrieved":1632130760627},{"title":"Runaway (Feat. Khundi Panda, Young Jay)","contents":"<!--fragment#10585021210#head-->Kiyoto<!--fragment#10585021210#tail-->","link":"https://www.music-flo.com/detail/album/edzllzlae/albumtrack","retrieved":1632195622931},{"title":"ON & ON","contents":"<!--fragment#166dbd066dc#head-->보라미유<!--fragment#166dbd066dc#tail-->","link":"https://www.music-flo.com/detail/album/edzllzhii/albumtrack","retrieved":1632130760628},{"title":"영혼이, 영원히 살어","contents":"<!--fragment#970bf317c4#head-->Keith Ape (Kid Ash)<!--fragment#970bf317c4#tail-->","link":"https://www.music-flo.com/detail/album/edzllidli/albumtrack","retrieved":1632130760629},{"title":"sea of info","contents":"<!--fragment#14eeec880de#head-->JISOKURY<!--fragment#14eeec880de#tail-->","link":"https://www.music-flo.com/detail/album/edzllnyyl/albumtrack","retrieved":1632195622893},{"title":"콜이야","contents":"<!--fragment#154bc0420b6#head-->박성연<!--fragment#154bc0420b6#tail-->","link":"https://www.music-flo.com/detail/album/edzllzyhi/albumtrack","retrieved":1632130760639},{"title":"Ariel","contents":"<!--fragment#ac083d3744#head-->Suji x Yuna (수지유나)<!--fragment#ac083d3744#tail-->","link":"https://www.music-flo.com/detail/album/edzlllnzo/albumtrack","retrieved":1632195622896},{"title":"여자이고 싶은걸 (Loving you)","contents":"<!--fragment#ec044b48dd#head-->유키카<!--fragment#ec044b48dd#tail-->","link":"https://www.music-flo.com/detail/album/edzllziei/albumtrack","retrieved":1632130760640},{"title":"망각","contents":"<!--fragment#119fa94e89e#head-->차윤섭<!--fragment#119fa94e89e#tail-->","link":"https://www.music-flo.com/detail/album/edzllnehz/albumtrack","retrieved":1632195622896},{"title":"내게도 올거야 (With 전현재, 8C)","contents":"<!--fragment#b8a0f09f26#head-->우찬양<!--fragment#b8a0f09f26#tail-->","link":"https://www.music-flo.com/detail/album/edzleznoa/albumtrack","retrieved":1632195622896},{"title":"DRIP (24) (Feat. playasian)","contents":"<!--fragment#a403a976be#head-->KROM<!--fragment#a403a976be#tail-->","link":"https://www.music-flo.com/detail/album/edzllllao/albumtrack","retrieved":1632195622896},{"title":"불꽃","contents":"<!--fragment#66ab570c0b#head-->명이월 (Myeong E-Wol)<!--fragment#66ab570c0b#tail-->","link":"https://www.music-flo.com/detail/album/edzllayie/albumtrack","retrieved":1632130760641},{"title":"그대의 날개가 되어","contents":"<!--fragment#a52536dc2e#head-->고영열<!--fragment#a52536dc2e#tail-->","link":"https://www.music-flo.com/detail/album/edzllniyl/albumtrack","retrieved":1632109231106},{"title":"화;월 (花月)","contents":"<!--fragment#154f3ef6ca7#head-->우예린<!--fragment#154f3ef6ca7#tail-->","link":"https://www.music-flo.com/detail/album/edzllnlid/albumtrack","retrieved":1632109231108},{"title":"Full of scars (Feat.Lil Gimchi)","contents":"<!--fragment#2884d8c02a#head-->YLN Foreign<!--fragment#2884d8c02a#tail-->","link":"https://www.music-flo.com/detail/album/edzllzdya/albumtrack","retrieved":1632109231109},{"title":"Lifetime (Original Track by Romy)","contents":"<!--fragment#2c16df7bed#head-->CIFIKA<!--fragment#2c16df7bed#tail-->","link":"https://www.music-flo.com/detail/album/edzlioyaz/albumtrack","retrieved":1632109231107},{"title":"찰나가 영원이 될 때 (The Eternal Moment)","contents":"<!--fragment#fd21dbd4ea#head-->마크툽 (MAKTUB)<!--fragment#fd21dbd4ea#tail-->","link":"https://www.music-flo.com/detail/album/edzllneoy/albumtrack","retrieved":1632044316564},{"title":"My Romance","contents":"<!--fragment#598c95b5b#head-->CHEEZE (치즈)<!--fragment#598c95b5b#tail-->","link":"https://www.music-flo.com/detail/album/edzllldyh/albumtrack","retrieved":1632044316565},{"title":"profile (Prod. entoy)","contents":"<!--fragment#ce725de174#head-->Mabinc<!--fragment#ce725de174#tail-->","link":"https://www.music-flo.com/detail/album/edzllniih/albumtrack","retrieved":1632109231038},{"title":"그날 그밤","contents":"<!--fragment#1614a733282#head-->DK<!--fragment#1614a733282#tail-->","link":"https://www.music-flo.com/detail/album/edzllzydn/albumtrack","retrieved":1632044316567},{"title":"시간은 (Time Is) (Feat. 모건 (mogun) of richeXcrown)","contents":"<!--fragment#efec8679eb#head-->PicoVello<!--fragment#efec8679eb#tail-->","link":"https://www.music-flo.com/detail/album/edzlllnhn/albumtrack","retrieved":1632109231032}]}